<?xml version="1.0" encoding="utf-8"?>
<!DOCTYPE rrd SYSTEM "https://oss.oetiker.ch/rrdtool/rrdtool.dtd">
<!-- Round Robin Database Dump -->
<rrd>
	<version>0003</version>
	<step>5</step> <!-- Seconds -->
	<lastupdate>1667999322</lastupdate> <!-- 2022-11-09 07:08:42 CST -->

	<ds>
		<name> unicast </name>
		<type> COUNTER </type>
		<minimal_heartbeat>120</minimal_heartbeat>
		<min>NaN</min>
		<max>NaN</max>

		<!-- PDP Status -->
		<last_ds>11938</last_ds>
		<value>3.4000000000e+01</value>
		<unknown_sec> 0 </unknown_sec>
	</ds>

	<ds>
		<name> ip </name>
		<type> COUNTER </type>
		<minimal_heartbeat>120</minimal_heartbeat>
		<min>NaN</min>
		<max>NaN</max>

		<!-- PDP Status -->
		<last_ds>6</last_ds>
		<value>0.0000000000e+00</value>
		<unknown_sec> 0 </unknown_sec>
	</ds>

	<ds>
		<name> icmp </name>
		<type> COUNTER </type>
		<minimal_heartbeat>120</minimal_heartbeat>
		<min>NaN</min>
		<max>NaN</max>

		<!-- PDP Status -->
		<last_ds>0</last_ds>
		<value>0.0000000000e+00</value>
		<unknown_sec> 0 </unknown_sec>
	</ds>

	<ds>
		<name> segmentos </name>
		<type> COUNTER </type>
		<minimal_heartbeat>120</minimal_heartbeat>
		<min>NaN</min>
		<max>NaN</max>

		<!-- PDP Status -->
		<last_ds>386472</last_ds>
		<value>0.0000000000e+00</value>
		<unknown_sec> 0 </unknown_sec>
	</ds>

	<ds>
		<name> datagramas </name>
		<type> COUNTER </type>
		<minimal_heartbeat>120</minimal_heartbeat>
		<min>NaN</min>
		<max>NaN</max>

		<!-- PDP Status -->
		<last_ds>31955</last_ds>
		<value>0.0000000000e+00</value>
		<unknown_sec> 0 </unknown_sec>
	</ds>

	<!-- Round Robin Archives -->
	<rra>
		<cf>AVERAGE</cf>
		<pdp_per_row>10</pdp_per_row> <!-- 50 seconds -->

		<params>
		<xff>4.0000000000e-01</xff>
		</params>
		<cdp_prep>
			<ds>
			<primary_value>1.1577904709e+01</primary_value>
			<secondary_value>1.0979047090e+01</secondary_value>
			<value>4.4220952910e+01</value>
			<unknown_datapoints>0</unknown_datapoints>
			</ds>
			<ds>
			<primary_value>0.0000000000e+00</primary_value>
			<secondary_value>0.0000000000e+00</secondary_value>
			<value>0.0000000000e+00</value>
			<unknown_datapoints>0</unknown_datapoints>
			</ds>
			<ds>
			<primary_value>0.0000000000e+00</primary_value>
			<secondary_value>0.0000000000e+00</secondary_value>
			<value>0.0000000000e+00</value>
			<unknown_datapoints>0</unknown_datapoints>
			</ds>
			<ds>
			<primary_value>2.6200000000e+00</primary_value>
			<secondary_value>2.6000000000e+00</secondary_value>
			<value>9.6000000000e+00</value>
			<unknown_datapoints>0</unknown_datapoints>
			</ds>
			<ds>
			<primary_value>1.1080000000e+01</primary_value>
			<secondary_value>1.0000000000e+01</secondary_value>
			<value>4.1400000000e+01</value>
			<unknown_datapoints>0</unknown_datapoints>
			</ds>
		</cdp_prep>
		<database>
			<!-- 2022-11-09 05:45:50 CST / 1667994350 --> <row><v>NaN</v><v>NaN</v><v>NaN</v><v>NaN</v><v>NaN</v></row>
			<!-- 2022-11-09 05:46:40 CST / 1667994400 --> <row><v>NaN</v><v>NaN</v><v>NaN</v><v>NaN</v><v>NaN</v></row>
			<!-- 2022-11-09 05:47:30 CST / 1667994450 --> <row><v>NaN</v><v>NaN</v><v>NaN</v><v>NaN</v><v>NaN</v></row>
			<!-- 2022-11-09 05:48:20 CST / 1667994500 --> <row><v>NaN</v><v>NaN</v><v>NaN</v><v>NaN</v><v>NaN</v></row>
			<!-- 2022-11-09 05:49:10 CST / 1667994550 --> <row><v>NaN</v><v>NaN</v><v>NaN</v><v>NaN</v><v>NaN</v></row>
			<!-- 2022-11-09 05:50:00 CST / 1667994600 --> <row><v>NaN</v><v>NaN</v><v>NaN</v><v>NaN</v><v>NaN</v></row>
			<!-- 2022-11-09 05:50:50 CST / 1667994650 --> <row><v>NaN</v><v>NaN</v><v>NaN</v><v>NaN</v><v>NaN</v></row>
			<!-- 2022-11-09 05:51:40 CST / 1667994700 --> <row><v>NaN</v><v>NaN</v><v>NaN</v><v>NaN</v><v>NaN</v></row>
			<!-- 2022-11-09 05:52:30 CST / 1667994750 --> <row><v>NaN</v><v>NaN</v><v>NaN</v><v>NaN</v><v>NaN</v></row>
			<!-- 2022-11-09 05:53:20 CST / 1667994800 --> <row><v>NaN</v><v>NaN</v><v>NaN</v><v>NaN</v><v>NaN</v></row>
			<!-- 2022-11-09 05:54:10 CST / 1667994850 --> <row><v>NaN</v><v>NaN</v><v>NaN</v><v>NaN</v><v>NaN</v></row>
			<!-- 2022-11-09 05:55:00 CST / 1667994900 --> <row><v>NaN</v><v>NaN</v><v>NaN</v><v>NaN</v><v>NaN</v></row>
			<!-- 2022-11-09 05:55:50 CST / 1667994950 --> <row><v>NaN</v><v>NaN</v><v>NaN</v><v>NaN</v><v>NaN</v></row>
			<!-- 2022-11-09 05:56:40 CST / 1667995000 --> <row><v>NaN</v><v>NaN</v><v>NaN</v><v>NaN</v><v>NaN</v></row>
			<!-- 2022-11-09 05:57:30 CST / 1667995050 --> <row><v>NaN</v><v>NaN</v><v>NaN</v><v>NaN</v><v>NaN</v></row>
			<!-- 2022-11-09 05:58:20 CST / 1667995100 --> <row><v>NaN</v><v>NaN</v><v>NaN</v><v>NaN</v><v>NaN</v></row>
			<!-- 2022-11-09 05:59:10 CST / 1667995150 --> <row><v>NaN</v><v>NaN</v><v>NaN</v><v>NaN</v><v>NaN</v></row>
			<!-- 2022-11-09 06:00:00 CST / 1667995200 --> <row><v>NaN</v><v>NaN</v><v>NaN</v><v>NaN</v><v>NaN</v></row>
			<!-- 2022-11-09 06:00:50 CST / 1667995250 --> <row><v>NaN</v><v>NaN</v><v>NaN</v><v>NaN</v><v>NaN</v></row>
			<!-- 2022-11-09 06:01:40 CST / 1667995300 --> <row><v>NaN</v><v>NaN</v><v>NaN</v><v>NaN</v><v>NaN</v></row>
			<!-- 2022-11-09 06:02:30 CST / 1667995350 --> <row><v>NaN</v><v>NaN</v><v>NaN</v><v>NaN</v><v>NaN</v></row>
			<!-- 2022-11-09 06:03:20 CST / 1667995400 --> <row><v>NaN</v><v>NaN</v><v>NaN</v><v>NaN</v><v>NaN</v></row>
			<!-- 2022-11-09 06:04:10 CST / 1667995450 --> <row><v>NaN</v><v>NaN</v><v>NaN</v><v>NaN</v><v>NaN</v></row>
			<!-- 2022-11-09 06:05:00 CST / 1667995500 --> <row><v>NaN</v><v>NaN</v><v>NaN</v><v>NaN</v><v>NaN</v></row>
			<!-- 2022-11-09 06:05:50 CST / 1667995550 --> <row><v>NaN</v><v>NaN</v><v>NaN</v><v>NaN</v><v>NaN</v></row>
			<!-- 2022-11-09 06:06:40 CST / 1667995600 --> <row><v>NaN</v><v>NaN</v><v>NaN</v><v>NaN</v><v>NaN</v></row>
			<!-- 2022-11-09 06:07:30 CST / 1667995650 --> <row><v>NaN</v><v>NaN</v><v>NaN</v><v>NaN</v><v>NaN</v></row>
			<!-- 2022-11-09 06:08:20 CST / 1667995700 --> <row><v>NaN</v><v>NaN</v><v>NaN</v><v>NaN</v><v>NaN</v></row>
			<!-- 2022-11-09 06:09:10 CST / 1667995750 --> <row><v>NaN</v><v>NaN</v><v>NaN</v><v>NaN</v><v>NaN</v></row>
			<!-- 2022-11-09 06:10:00 CST / 1667995800 --> <row><v>NaN</v><v>NaN</v><v>NaN</v><v>NaN</v><v>NaN</v></row>
			<!-- 2022-11-09 06:10:50 CST / 1667995850 --> <row><v>NaN</v><v>NaN</v><v>NaN</v><v>NaN</v><v>NaN</v></row>
			<!-- 2022-11-09 06:11:40 CST / 1667995900 --> <row><v>NaN</v><v>NaN</v><v>NaN</v><v>NaN</v><v>NaN</v></row>
			<!-- 2022-11-09 06:12:30 CST / 1667995950 --> <row><v>NaN</v><v>NaN</v><v>NaN</v><v>NaN</v><v>NaN</v></row>
			<!-- 2022-11-09 06:13:20 CST / 1667996000 --> <row><v>NaN</v><v>NaN</v><v>NaN</v><v>NaN</v><v>NaN</v></row>
			<!-- 2022-11-09 06:14:10 CST / 1667996050 --> <row><v>NaN</v><v>NaN</v><v>NaN</v><v>NaN</v><v>NaN</v></row>
			<!-- 2022-11-09 06:15:00 CST / 1667996100 --> <row><v>NaN</v><v>NaN</v><v>NaN</v><v>NaN</v><v>NaN</v></row>
			<!-- 2022-11-09 06:15:50 CST / 1667996150 --> <row><v>NaN</v><v>NaN</v><v>NaN</v><v>NaN</v><v>NaN</v></row>
			<!-- 2022-11-09 06:16:40 CST / 1667996200 --> <row><v>NaN</v><v>NaN</v><v>NaN</v><v>NaN</v><v>NaN</v></row>
			<!-- 2022-11-09 06:17:30 CST / 1667996250 --> <row><v>NaN</v><v>NaN</v><v>NaN</v><v>NaN</v><v>NaN</v></row>
			<!-- 2022-11-09 06:18:20 CST / 1667996300 --> <row><v>NaN</v><v>NaN</v><v>NaN</v><v>NaN</v><v>NaN</v></row>
			<!-- 2022-11-09 06:19:10 CST / 1667996350 --> <row><v>NaN</v><v>NaN</v><v>NaN</v><v>NaN</v><v>NaN</v></row>
			<!-- 2022-11-09 06:20:00 CST / 1667996400 --> <row><v>NaN</v><v>NaN</v><v>NaN</v><v>NaN</v><v>NaN</v></row>
			<!-- 2022-11-09 06:20:50 CST / 1667996450 --> <row><v>NaN</v><v>NaN</v><v>NaN</v><v>NaN</v><v>NaN</v></row>
			<!-- 2022-11-09 06:21:40 CST / 1667996500 --> <row><v>NaN</v><v>NaN</v><v>NaN</v><v>NaN</v><v>NaN</v></row>
			<!-- 2022-11-09 06:22:30 CST / 1667996550 --> <row><v>NaN</v><v>NaN</v><v>NaN</v><v>NaN</v><v>NaN</v></row>
			<!-- 2022-11-09 06:23:20 CST / 1667996600 --> <row><v>NaN</v><v>NaN</v><v>NaN</v><v>NaN</v><v>NaN</v></row>
			<!-- 2022-11-09 06:24:10 CST / 1667996650 --> <row><v>NaN</v><v>NaN</v><v>NaN</v><v>NaN</v><v>NaN</v></row>
			<!-- 2022-11-09 06:25:00 CST / 1667996700 --> <row><v>NaN</v><v>NaN</v><v>NaN</v><v>NaN</v><v>NaN</v></row>
			<!-- 2022-11-09 06:25:50 CST / 1667996750 --> <row><v>NaN</v><v>NaN</v><v>NaN</v><v>NaN</v><v>NaN</v></row>
			<!-- 2022-11-09 06:26:40 CST / 1667996800 --> <row><v>NaN</v><v>NaN</v><v>NaN</v><v>NaN</v><v>NaN</v></row>
			<!-- 2022-11-09 06:27:30 CST / 1667996850 --> <row><v>NaN</v><v>NaN</v><v>NaN</v><v>NaN</v><v>NaN</v></row>
			<!-- 2022-11-09 06:28:20 CST / 1667996900 --> <row><v>NaN</v><v>NaN</v><v>NaN</v><v>NaN</v><v>NaN</v></row>
			<!-- 2022-11-09 06:29:10 CST / 1667996950 --> <row><v>NaN</v><v>NaN</v><v>NaN</v><v>NaN</v><v>NaN</v></row>
			<!-- 2022-11-09 06:30:00 CST / 1667997000 --> <row><v>NaN</v><v>NaN</v><v>NaN</v><v>NaN</v><v>NaN</v></row>
			<!-- 2022-11-09 06:30:50 CST / 1667997050 --> <row><v>NaN</v><v>NaN</v><v>NaN</v><v>NaN</v><v>NaN</v></row>
			<!-- 2022-11-09 06:31:40 CST / 1667997100 --> <row><v>NaN</v><v>NaN</v><v>NaN</v><v>NaN</v><v>NaN</v></row>
			<!-- 2022-11-09 06:32:30 CST / 1667997150 --> <row><v>NaN</v><v>NaN</v><v>NaN</v><v>NaN</v><v>NaN</v></row>
			<!-- 2022-11-09 06:33:20 CST / 1667997200 --> <row><v>NaN</v><v>NaN</v><v>NaN</v><v>NaN</v><v>NaN</v></row>
			<!-- 2022-11-09 06:34:10 CST / 1667997250 --> <row><v>NaN</v><v>NaN</v><v>NaN</v><v>NaN</v><v>NaN</v></row>
			<!-- 2022-11-09 06:35:00 CST / 1667997300 --> <row><v>NaN</v><v>NaN</v><v>NaN</v><v>NaN</v><v>NaN</v></row>
			<!-- 2022-11-09 06:35:50 CST / 1667997350 --> <row><v>NaN</v><v>NaN</v><v>NaN</v><v>NaN</v><v>NaN</v></row>
			<!-- 2022-11-09 06:36:40 CST / 1667997400 --> <row><v>NaN</v><v>NaN</v><v>NaN</v><v>NaN</v><v>NaN</v></row>
			<!-- 2022-11-09 06:37:30 CST / 1667997450 --> <row><v>NaN</v><v>NaN</v><v>NaN</v><v>NaN</v><v>NaN</v></row>
			<!-- 2022-11-09 06:38:20 CST / 1667997500 --> <row><v>NaN</v><v>NaN</v><v>NaN</v><v>NaN</v><v>NaN</v></row>
			<!-- 2022-11-09 06:39:10 CST / 1667997550 --> <row><v>NaN</v><v>NaN</v><v>NaN</v><v>NaN</v><v>NaN</v></row>
			<!-- 2022-11-09 06:40:00 CST / 1667997600 --> <row><v>NaN</v><v>NaN</v><v>NaN</v><v>NaN</v><v>NaN</v></row>
			<!-- 2022-11-09 06:40:50 CST / 1667997650 --> <row><v>NaN</v><v>NaN</v><v>NaN</v><v>NaN</v><v>NaN</v></row>
			<!-- 2022-11-09 06:41:40 CST / 1667997700 --> <row><v>NaN</v><v>NaN</v><v>NaN</v><v>NaN</v><v>NaN</v></row>
			<!-- 2022-11-09 06:42:30 CST / 1667997750 --> <row><v>NaN</v><v>NaN</v><v>NaN</v><v>NaN</v><v>NaN</v></row>
			<!-- 2022-11-09 06:43:20 CST / 1667997800 --> <row><v>NaN</v><v>NaN</v><v>NaN</v><v>NaN</v><v>NaN</v></row>
			<!-- 2022-11-09 06:44:10 CST / 1667997850 --> <row><v>NaN</v><v>NaN</v><v>NaN</v><v>NaN</v><v>NaN</v></row>
			<!-- 2022-11-09 06:45:00 CST / 1667997900 --> <row><v>NaN</v><v>NaN</v><v>NaN</v><v>NaN</v><v>NaN</v></row>
			<!-- 2022-11-09 06:45:50 CST / 1667997950 --> <row><v>NaN</v><v>NaN</v><v>NaN</v><v>NaN</v><v>NaN</v></row>
			<!-- 2022-11-09 06:46:40 CST / 1667998000 --> <row><v>NaN</v><v>NaN</v><v>NaN</v><v>NaN</v><v>NaN</v></row>
			<!-- 2022-11-09 06:47:30 CST / 1667998050 --> <row><v>NaN</v><v>NaN</v><v>NaN</v><v>NaN</v><v>NaN</v></row>
			<!-- 2022-11-09 06:48:20 CST / 1667998100 --> <row><v>NaN</v><v>NaN</v><v>NaN</v><v>NaN</v><v>NaN</v></row>
			<!-- 2022-11-09 06:49:10 CST / 1667998150 --> <row><v>NaN</v><v>NaN</v><v>NaN</v><v>NaN</v><v>NaN</v></row>
			<!-- 2022-11-09 06:50:00 CST / 1667998200 --> <row><v>NaN</v><v>NaN</v><v>NaN</v><v>NaN</v><v>NaN</v></row>
			<!-- 2022-11-09 06:50:50 CST / 1667998250 --> <row><v>NaN</v><v>NaN</v><v>NaN</v><v>NaN</v><v>NaN</v></row>
			<!-- 2022-11-09 06:51:40 CST / 1667998300 --> <row><v>NaN</v><v>NaN</v><v>NaN</v><v>NaN</v><v>NaN</v></row>
			<!-- 2022-11-09 06:52:30 CST / 1667998350 --> <row><v>NaN</v><v>NaN</v><v>NaN</v><v>NaN</v><v>NaN</v></row>
			<!-- 2022-11-09 06:53:20 CST / 1667998400 --> <row><v>NaN</v><v>NaN</v><v>NaN</v><v>NaN</v><v>NaN</v></row>
			<!-- 2022-11-09 06:54:10 CST / 1667998450 --> <row><v>NaN</v><v>NaN</v><v>NaN</v><v>NaN</v><v>NaN</v></row>
			<!-- 2022-11-09 06:55:00 CST / 1667998500 --> <row><v>NaN</v><v>NaN</v><v>NaN</v><v>NaN</v><v>NaN</v></row>
			<!-- 2022-11-09 06:55:50 CST / 1667998550 --> <row><v>NaN</v><v>NaN</v><v>NaN</v><v>NaN</v><v>NaN</v></row>
			<!-- 2022-11-09 06:56:40 CST / 1667998600 --> <row><v>NaN</v><v>NaN</v><v>NaN</v><v>NaN</v><v>NaN</v></row>
			<!-- 2022-11-09 06:57:30 CST / 1667998650 --> <row><v>NaN</v><v>NaN</v><v>NaN</v><v>NaN</v><v>NaN</v></row>
			<!-- 2022-11-09 06:58:20 CST / 1667998700 --> <row><v>NaN</v><v>NaN</v><v>NaN</v><v>NaN</v><v>NaN</v></row>
			<!-- 2022-11-09 06:59:10 CST / 1667998750 --> <row><v>NaN</v><v>NaN</v><v>NaN</v><v>NaN</v><v>NaN</v></row>
			<!-- 2022-11-09 07:00:00 CST / 1667998800 --> <row><v>NaN</v><v>NaN</v><v>NaN</v><v>NaN</v><v>NaN</v></row>
			<!-- 2022-11-09 07:00:50 CST / 1667998850 --> <row><v>NaN</v><v>NaN</v><v>NaN</v><v>NaN</v><v>NaN</v></row>
			<!-- 2022-11-09 07:01:40 CST / 1667998900 --> <row><v>NaN</v><v>NaN</v><v>NaN</v><v>NaN</v><v>NaN</v></row>
			<!-- 2022-11-09 07:02:30 CST / 1667998950 --> <row><v>NaN</v><v>NaN</v><v>NaN</v><v>NaN</v><v>NaN</v></row>
			<!-- 2022-11-09 07:03:20 CST / 1667999000 --> <row><v>NaN</v><v>NaN</v><v>NaN</v><v>NaN</v><v>NaN</v></row>
			<!-- 2022-11-09 07:04:10 CST / 1667999050 --> <row><v>NaN</v><v>NaN</v><v>NaN</v><v>NaN</v><v>NaN</v></row>
			<!-- 2022-11-09 07:05:00 CST / 1667999100 --> <row><v>NaN</v><v>NaN</v><v>NaN</v><v>NaN</v><v>NaN</v></row>
			<!-- 2022-11-09 07:05:50 CST / 1667999150 --> <row><v>NaN</v><v>NaN</v><v>NaN</v><v>NaN</v><v>NaN</v></row>
			<!-- 2022-11-09 07:06:40 CST / 1667999200 --> <row><v>NaN</v><v>NaN</v><v>NaN</v><v>NaN</v><v>NaN</v></row>
			<!-- 2022-11-09 07:07:30 CST / 1667999250 --> <row><v>1.1210000000e+01</v><v>0.0000000000e+00</v><v>0.0000000000e+00</v><v>2.5400000000e+00</v><v>9.4200000000e+00</v></row>
			<!-- 2022-11-09 07:08:20 CST / 1667999300 --> <row><v>1.1577904709e+01</v><v>0.0000000000e+00</v><v>0.0000000000e+00</v><v>2.6200000000e+00</v><v>1.1080000000e+01</v></row>
		</database>
	</rra>
	<rra>
		<cf>AVERAGE</cf>
		<pdp_per_row>10</pdp_per_row> <!-- 50 seconds -->

		<params>
		<xff>4.0000000000e-01</xff>
		</params>
		<cdp_prep>
			<ds>
			<primary_value>1.1577904709e+01</primary_value>
			<secondary_value>1.0979047090e+01</secondary_value>
			<value>4.4220952910e+01</value>
			<unknown_datapoints>0</unknown_datapoints>
			</ds>
			<ds>
			<primary_value>0.0000000000e+00</primary_value>
			<secondary_value>0.0000000000e+00</secondary_value>
			<value>0.0000000000e+00</value>
			<unknown_datapoints>0</unknown_datapoints>
			</ds>
			<ds>
			<primary_value>0.0000000000e+00</primary_value>
			<secondary_value>0.0000000000e+00</secondary_value>
			<value>0.0000000000e+00</value>
			<unknown_datapoints>0</unknown_datapoints>
			</ds>
			<ds>
			<primary_value>2.6200000000e+00</primary_value>
			<secondary_value>2.6000000000e+00</secondary_value>
			<value>9.6000000000e+00</value>
			<unknown_datapoints>0</unknown_datapoints>
			</ds>
			<ds>
			<primary_value>1.1080000000e+01</primary_value>
			<secondary_value>1.0000000000e+01</secondary_value>
			<value>4.1400000000e+01</value>
			<unknown_datapoints>0</unknown_datapoints>
			</ds>
		</cdp_prep>
		<database>
			<!-- 2022-11-09 05:45:50 CST / 1667994350 --> <row><v>NaN</v><v>NaN</v><v>NaN</v><v>NaN</v><v>NaN</v></row>
			<!-- 2022-11-09 05:46:40 CST / 1667994400 --> <row><v>NaN</v><v>NaN</v><v>NaN</v><v>NaN</v><v>NaN</v></row>
			<!-- 2022-11-09 05:47:30 CST / 1667994450 --> <row><v>NaN</v><v>NaN</v><v>NaN</v><v>NaN</v><v>NaN</v></row>
			<!-- 2022-11-09 05:48:20 CST / 1667994500 --> <row><v>NaN</v><v>NaN</v><v>NaN</v><v>NaN</v><v>NaN</v></row>
			<!-- 2022-11-09 05:49:10 CST / 1667994550 --> <row><v>NaN</v><v>NaN</v><v>NaN</v><v>NaN</v><v>NaN</v></row>
			<!-- 2022-11-09 05:50:00 CST / 1667994600 --> <row><v>NaN</v><v>NaN</v><v>NaN</v><v>NaN</v><v>NaN</v></row>
			<!-- 2022-11-09 05:50:50 CST / 1667994650 --> <row><v>NaN</v><v>NaN</v><v>NaN</v><v>NaN</v><v>NaN</v></row>
			<!-- 2022-11-09 05:51:40 CST / 1667994700 --> <row><v>NaN</v><v>NaN</v><v>NaN</v><v>NaN</v><v>NaN</v></row>
			<!-- 2022-11-09 05:52:30 CST / 1667994750 --> <row><v>NaN</v><v>NaN</v><v>NaN</v><v>NaN</v><v>NaN</v></row>
			<!-- 2022-11-09 05:53:20 CST / 1667994800 --> <row><v>NaN</v><v>NaN</v><v>NaN</v><v>NaN</v><v>NaN</v></row>
			<!-- 2022-11-09 05:54:10 CST / 1667994850 --> <row><v>NaN</v><v>NaN</v><v>NaN</v><v>NaN</v><v>NaN</v></row>
			<!-- 2022-11-09 05:55:00 CST / 1667994900 --> <row><v>NaN</v><v>NaN</v><v>NaN</v><v>NaN</v><v>NaN</v></row>
			<!-- 2022-11-09 05:55:50 CST / 1667994950 --> <row><v>NaN</v><v>NaN</v><v>NaN</v><v>NaN</v><v>NaN</v></row>
			<!-- 2022-11-09 05:56:40 CST / 1667995000 --> <row><v>NaN</v><v>NaN</v><v>NaN</v><v>NaN</v><v>NaN</v></row>
			<!-- 2022-11-09 05:57:30 CST / 1667995050 --> <row><v>NaN</v><v>NaN</v><v>NaN</v><v>NaN</v><v>NaN</v></row>
			<!-- 2022-11-09 05:58:20 CST / 1667995100 --> <row><v>NaN</v><v>NaN</v><v>NaN</v><v>NaN</v><v>NaN</v></row>
			<!-- 2022-11-09 05:59:10 CST / 1667995150 --> <row><v>NaN</v><v>NaN</v><v>NaN</v><v>NaN</v><v>NaN</v></row>
			<!-- 2022-11-09 06:00:00 CST / 1667995200 --> <row><v>NaN</v><v>NaN</v><v>NaN</v><v>NaN</v><v>NaN</v></row>
			<!-- 2022-11-09 06:00:50 CST / 1667995250 --> <row><v>NaN</v><v>NaN</v><v>NaN</v><v>NaN</v><v>NaN</v></row>
			<!-- 2022-11-09 06:01:40 CST / 1667995300 --> <row><v>NaN</v><v>NaN</v><v>NaN</v><v>NaN</v><v>NaN</v></row>
			<!-- 2022-11-09 06:02:30 CST / 1667995350 --> <row><v>NaN</v><v>NaN</v><v>NaN</v><v>NaN</v><v>NaN</v></row>
			<!-- 2022-11-09 06:03:20 CST / 1667995400 --> <row><v>NaN</v><v>NaN</v><v>NaN</v><v>NaN</v><v>NaN</v></row>
			<!-- 2022-11-09 06:04:10 CST / 1667995450 --> <row><v>NaN</v><v>NaN</v><v>NaN</v><v>NaN</v><v>NaN</v></row>
			<!-- 2022-11-09 06:05:00 CST / 1667995500 --> <row><v>NaN</v><v>NaN</v><v>NaN</v><v>NaN</v><v>NaN</v></row>
			<!-- 2022-11-09 06:05:50 CST / 1667995550 --> <row><v>NaN</v><v>NaN</v><v>NaN</v><v>NaN</v><v>NaN</v></row>
			<!-- 2022-11-09 06:06:40 CST / 1667995600 --> <row><v>NaN</v><v>NaN</v><v>NaN</v><v>NaN</v><v>NaN</v></row>
			<!-- 2022-11-09 06:07:30 CST / 1667995650 --> <row><v>NaN</v><v>NaN</v><v>NaN</v><v>NaN</v><v>NaN</v></row>
			<!-- 2022-11-09 06:08:20 CST / 1667995700 --> <row><v>NaN</v><v>NaN</v><v>NaN</v><v>NaN</v><v>NaN</v></row>
			<!-- 2022-11-09 06:09:10 CST / 1667995750 --> <row><v>NaN</v><v>NaN</v><v>NaN</v><v>NaN</v><v>NaN</v></row>
			<!-- 2022-11-09 06:10:00 CST / 1667995800 --> <row><v>NaN</v><v>NaN</v><v>NaN</v><v>NaN</v><v>NaN</v></row>
			<!-- 2022-11-09 06:10:50 CST / 1667995850 --> <row><v>NaN</v><v>NaN</v><v>NaN</v><v>NaN</v><v>NaN</v></row>
			<!-- 2022-11-09 06:11:40 CST / 1667995900 --> <row><v>NaN</v><v>NaN</v><v>NaN</v><v>NaN</v><v>NaN</v></row>
			<!-- 2022-11-09 06:12:30 CST / 1667995950 --> <row><v>NaN</v><v>NaN</v><v>NaN</v><v>NaN</v><v>NaN</v></row>
			<!-- 2022-11-09 06:13:20 CST / 1667996000 --> <row><v>NaN</v><v>NaN</v><v>NaN</v><v>NaN</v><v>NaN</v></row>
			<!-- 2022-11-09 06:14:10 CST / 1667996050 --> <row><v>NaN</v><v>NaN</v><v>NaN</v><v>NaN</v><v>NaN</v></row>
			<!-- 2022-11-09 06:15:00 CST / 1667996100 --> <row><v>NaN</v><v>NaN</v><v>NaN</v><v>NaN</v><v>NaN</v></row>
			<!-- 2022-11-09 06:15:50 CST / 1667996150 --> <row><v>NaN</v><v>NaN</v><v>NaN</v><v>NaN</v><v>NaN</v></row>
			<!-- 2022-11-09 06:16:40 CST / 1667996200 --> <row><v>NaN</v><v>NaN</v><v>NaN</v><v>NaN</v><v>NaN</v></row>
			<!-- 2022-11-09 06:17:30 CST / 1667996250 --> <row><v>NaN</v><v>NaN</v><v>NaN</v><v>NaN</v><v>NaN</v></row>
			<!-- 2022-11-09 06:18:20 CST / 1667996300 --> <row><v>NaN</v><v>NaN</v><v>NaN</v><v>NaN</v><v>NaN</v></row>
			<!-- 2022-11-09 06:19:10 CST / 1667996350 --> <row><v>NaN</v><v>NaN</v><v>NaN</v><v>NaN</v><v>NaN</v></row>
			<!-- 2022-11-09 06:20:00 CST / 1667996400 --> <row><v>NaN</v><v>NaN</v><v>NaN</v><v>NaN</v><v>NaN</v></row>
			<!-- 2022-11-09 06:20:50 CST / 1667996450 --> <row><v>NaN</v><v>NaN</v><v>NaN</v><v>NaN</v><v>NaN</v></row>
			<!-- 2022-11-09 06:21:40 CST / 1667996500 --> <row><v>NaN</v><v>NaN</v><v>NaN</v><v>NaN</v><v>NaN</v></row>
			<!-- 2022-11-09 06:22:30 CST / 1667996550 --> <row><v>NaN</v><v>NaN</v><v>NaN</v><v>NaN</v><v>NaN</v></row>
			<!-- 2022-11-09 06:23:20 CST / 1667996600 --> <row><v>NaN</v><v>NaN</v><v>NaN</v><v>NaN</v><v>NaN</v></row>
			<!-- 2022-11-09 06:24:10 CST / 1667996650 --> <row><v>NaN</v><v>NaN</v><v>NaN</v><v>NaN</v><v>NaN</v></row>
			<!-- 2022-11-09 06:25:00 CST / 1667996700 --> <row><v>NaN</v><v>NaN</v><v>NaN</v><v>NaN</v><v>NaN</v></row>
			<!-- 2022-11-09 06:25:50 CST / 1667996750 --> <row><v>NaN</v><v>NaN</v><v>NaN</v><v>NaN</v><v>NaN</v></row>
			<!-- 2022-11-09 06:26:40 CST / 1667996800 --> <row><v>NaN</v><v>NaN</v><v>NaN</v><v>NaN</v><v>NaN</v></row>
			<!-- 2022-11-09 06:27:30 CST / 1667996850 --> <row><v>NaN</v><v>NaN</v><v>NaN</v><v>NaN</v><v>NaN</v></row>
			<!-- 2022-11-09 06:28:20 CST / 1667996900 --> <row><v>NaN</v><v>NaN</v><v>NaN</v><v>NaN</v><v>NaN</v></row>
			<!-- 2022-11-09 06:29:10 CST / 1667996950 --> <row><v>NaN</v><v>NaN</v><v>NaN</v><v>NaN</v><v>NaN</v></row>
			<!-- 2022-11-09 06:30:00 CST / 1667997000 --> <row><v>NaN</v><v>NaN</v><v>NaN</v><v>NaN</v><v>NaN</v></row>
			<!-- 2022-11-09 06:30:50 CST / 1667997050 --> <row><v>NaN</v><v>NaN</v><v>NaN</v><v>NaN</v><v>NaN</v></row>
			<!-- 2022-11-09 06:31:40 CST / 1667997100 --> <row><v>NaN</v><v>NaN</v><v>NaN</v><v>NaN</v><v>NaN</v></row>
			<!-- 2022-11-09 06:32:30 CST / 1667997150 --> <row><v>NaN</v><v>NaN</v><v>NaN</v><v>NaN</v><v>NaN</v></row>
			<!-- 2022-11-09 06:33:20 CST / 1667997200 --> <row><v>NaN</v><v>NaN</v><v>NaN</v><v>NaN</v><v>NaN</v></row>
			<!-- 2022-11-09 06:34:10 CST / 1667997250 --> <row><v>NaN</v><v>NaN</v><v>NaN</v><v>NaN</v><v>NaN</v></row>
			<!-- 2022-11-09 06:35:00 CST / 1667997300 --> <row><v>NaN</v><v>NaN</v><v>NaN</v><v>NaN</v><v>NaN</v></row>
			<!-- 2022-11-09 06:35:50 CST / 1667997350 --> <row><v>NaN</v><v>NaN</v><v>NaN</v><v>NaN</v><v>NaN</v></row>
			<!-- 2022-11-09 06:36:40 CST / 1667997400 --> <row><v>NaN</v><v>NaN</v><v>NaN</v><v>NaN</v><v>NaN</v></row>
			<!-- 2022-11-09 06:37:30 CST / 1667997450 --> <row><v>NaN</v><v>NaN</v><v>NaN</v><v>NaN</v><v>NaN</v></row>
			<!-- 2022-11-09 06:38:20 CST / 1667997500 --> <row><v>NaN</v><v>NaN</v><v>NaN</v><v>NaN</v><v>NaN</v></row>
			<!-- 2022-11-09 06:39:10 CST / 1667997550 --> <row><v>NaN</v><v>NaN</v><v>NaN</v><v>NaN</v><v>NaN</v></row>
			<!-- 2022-11-09 06:40:00 CST / 1667997600 --> <row><v>NaN</v><v>NaN</v><v>NaN</v><v>NaN</v><v>NaN</v></row>
			<!-- 2022-11-09 06:40:50 CST / 1667997650 --> <row><v>NaN</v><v>NaN</v><v>NaN</v><v>NaN</v><v>NaN</v></row>
			<!-- 2022-11-09 06:41:40 CST / 1667997700 --> <row><v>NaN</v><v>NaN</v><v>NaN</v><v>NaN</v><v>NaN</v></row>
			<!-- 2022-11-09 06:42:30 CST / 1667997750 --> <row><v>NaN</v><v>NaN</v><v>NaN</v><v>NaN</v><v>NaN</v></row>
			<!-- 2022-11-09 06:43:20 CST / 1667997800 --> <row><v>NaN</v><v>NaN</v><v>NaN</v><v>NaN</v><v>NaN</v></row>
			<!-- 2022-11-09 06:44:10 CST / 1667997850 --> <row><v>NaN</v><v>NaN</v><v>NaN</v><v>NaN</v><v>NaN</v></row>
			<!-- 2022-11-09 06:45:00 CST / 1667997900 --> <row><v>NaN</v><v>NaN</v><v>NaN</v><v>NaN</v><v>NaN</v></row>
			<!-- 2022-11-09 06:45:50 CST / 1667997950 --> <row><v>NaN</v><v>NaN</v><v>NaN</v><v>NaN</v><v>NaN</v></row>
			<!-- 2022-11-09 06:46:40 CST / 1667998000 --> <row><v>NaN</v><v>NaN</v><v>NaN</v><v>NaN</v><v>NaN</v></row>
			<!-- 2022-11-09 06:47:30 CST / 1667998050 --> <row><v>NaN</v><v>NaN</v><v>NaN</v><v>NaN</v><v>NaN</v></row>
			<!-- 2022-11-09 06:48:20 CST / 1667998100 --> <row><v>NaN</v><v>NaN</v><v>NaN</v><v>NaN</v><v>NaN</v></row>
			<!-- 2022-11-09 06:49:10 CST / 1667998150 --> <row><v>NaN</v><v>NaN</v><v>NaN</v><v>NaN</v><v>NaN</v></row>
			<!-- 2022-11-09 06:50:00 CST / 1667998200 --> <row><v>NaN</v><v>NaN</v><v>NaN</v><v>NaN</v><v>NaN</v></row>
			<!-- 2022-11-09 06:50:50 CST / 1667998250 --> <row><v>NaN</v><v>NaN</v><v>NaN</v><v>NaN</v><v>NaN</v></row>
			<!-- 2022-11-09 06:51:40 CST / 1667998300 --> <row><v>NaN</v><v>NaN</v><v>NaN</v><v>NaN</v><v>NaN</v></row>
			<!-- 2022-11-09 06:52:30 CST / 1667998350 --> <row><v>NaN</v><v>NaN</v><v>NaN</v><v>NaN</v><v>NaN</v></row>
			<!-- 2022-11-09 06:53:20 CST / 1667998400 --> <row><v>NaN</v><v>NaN</v><v>NaN</v><v>NaN</v><v>NaN</v></row>
			<!-- 2022-11-09 06:54:10 CST / 1667998450 --> <row><v>NaN</v><v>NaN</v><v>NaN</v><v>NaN</v><v>NaN</v></row>
			<!-- 2022-11-09 06:55:00 CST / 1667998500 --> <row><v>NaN</v><v>NaN</v><v>NaN</v><v>NaN</v><v>NaN</v></row>
			<!-- 2022-11-09 06:55:50 CST / 1667998550 --> <row><v>NaN</v><v>NaN</v><v>NaN</v><v>NaN</v><v>NaN</v></row>
			<!-- 2022-11-09 06:56:40 CST / 1667998600 --> <row><v>NaN</v><v>NaN</v><v>NaN</v><v>NaN</v><v>NaN</v></row>
			<!-- 2022-11-09 06:57:30 CST / 1667998650 --> <row><v>NaN</v><v>NaN</v><v>NaN</v><v>NaN</v><v>NaN</v></row>
			<!-- 2022-11-09 06:58:20 CST / 1667998700 --> <row><v>NaN</v><v>NaN</v><v>NaN</v><v>NaN</v><v>NaN</v></row>
			<!-- 2022-11-09 06:59:10 CST / 1667998750 --> <row><v>NaN</v><v>NaN</v><v>NaN</v><v>NaN</v><v>NaN</v></row>
			<!-- 2022-11-09 07:00:00 CST / 1667998800 --> <row><v>NaN</v><v>NaN</v><v>NaN</v><v>NaN</v><v>NaN</v></row>
			<!-- 2022-11-09 07:00:50 CST / 1667998850 --> <row><v>NaN</v><v>NaN</v><v>NaN</v><v>NaN</v><v>NaN</v></row>
			<!-- 2022-11-09 07:01:40 CST / 1667998900 --> <row><v>NaN</v><v>NaN</v><v>NaN</v><v>NaN</v><v>NaN</v></row>
			<!-- 2022-11-09 07:02:30 CST / 1667998950 --> <row><v>NaN</v><v>NaN</v><v>NaN</v><v>NaN</v><v>NaN</v></row>
			<!-- 2022-11-09 07:03:20 CST / 1667999000 --> <row><v>NaN</v><v>NaN</v><v>NaN</v><v>NaN</v><v>NaN</v></row>
			<!-- 2022-11-09 07:04:10 CST / 1667999050 --> <row><v>NaN</v><v>NaN</v><v>NaN</v><v>NaN</v><v>NaN</v></row>
			<!-- 2022-11-09 07:05:00 CST / 1667999100 --> <row><v>NaN</v><v>NaN</v><v>NaN</v><v>NaN</v><v>NaN</v></row>
			<!-- 2022-11-09 07:05:50 CST / 1667999150 --> <row><v>NaN</v><v>NaN</v><v>NaN</v><v>NaN</v><v>NaN</v></row>
			<!-- 2022-11-09 07:06:40 CST / 1667999200 --> <row><v>NaN</v><v>NaN</v><v>NaN</v><v>NaN</v><v>NaN</v></row>
			<!-- 2022-11-09 07:07:30 CST / 1667999250 --> <row><v>1.1210000000e+01</v><v>0.0000000000e+00</v><v>0.0000000000e+00</v><v>2.5400000000e+00</v><v>9.4200000000e+00</v></row>
			<!-- 2022-11-09 07:08:20 CST / 1667999300 --> <row><v>1.1577904709e+01</v><v>0.0000000000e+00</v><v>0.0000000000e+00</v><v>2.6200000000e+00</v><v>1.1080000000e+01</v></row>
		</database>
	</rra>
	<rra>
		<cf>AVERAGE</cf>
		<pdp_per_row>10</pdp_per_row> <!-- 50 seconds -->

		<params>
		<xff>4.0000000000e-01</xff>
		</params>
		<cdp_prep>
			<ds>
			<primary_value>1.1577904709e+01</primary_value>
			<secondary_value>1.0979047090e+01</secondary_value>
			<value>4.4220952910e+01</value>
			<unknown_datapoints>0</unknown_datapoints>
			</ds>
			<ds>
			<primary_value>0.0000000000e+00</primary_value>
			<secondary_value>0.0000000000e+00</secondary_value>
			<value>0.0000000000e+00</value>
			<unknown_datapoints>0</unknown_datapoints>
			</ds>
			<ds>
			<primary_value>0.0000000000e+00</primary_value>
			<secondary_value>0.0000000000e+00</secondary_value>
			<value>0.0000000000e+00</value>
			<unknown_datapoints>0</unknown_datapoints>
			</ds>
			<ds>
			<primary_value>2.6200000000e+00</primary_value>
			<secondary_value>2.6000000000e+00</secondary_value>
			<value>9.6000000000e+00</value>
			<unknown_datapoints>0</unknown_datapoints>
			</ds>
			<ds>
			<primary_value>1.1080000000e+01</primary_value>
			<secondary_value>1.0000000000e+01</secondary_value>
			<value>4.1400000000e+01</value>
			<unknown_datapoints>0</unknown_datapoints>
			</ds>
		</cdp_prep>
		<database>
			<!-- 2022-11-09 05:45:50 CST / 1667994350 --> <row><v>NaN</v><v>NaN</v><v>NaN</v><v>NaN</v><v>NaN</v></row>
			<!-- 2022-11-09 05:46:40 CST / 1667994400 --> <row><v>NaN</v><v>NaN</v><v>NaN</v><v>NaN</v><v>NaN</v></row>
			<!-- 2022-11-09 05:47:30 CST / 1667994450 --> <row><v>NaN</v><v>NaN</v><v>NaN</v><v>NaN</v><v>NaN</v></row>
			<!-- 2022-11-09 05:48:20 CST / 1667994500 --> <row><v>NaN</v><v>NaN</v><v>NaN</v><v>NaN</v><v>NaN</v></row>
			<!-- 2022-11-09 05:49:10 CST / 1667994550 --> <row><v>NaN</v><v>NaN</v><v>NaN</v><v>NaN</v><v>NaN</v></row>
			<!-- 2022-11-09 05:50:00 CST / 1667994600 --> <row><v>NaN</v><v>NaN</v><v>NaN</v><v>NaN</v><v>NaN</v></row>
			<!-- 2022-11-09 05:50:50 CST / 1667994650 --> <row><v>NaN</v><v>NaN</v><v>NaN</v><v>NaN</v><v>NaN</v></row>
			<!-- 2022-11-09 05:51:40 CST / 1667994700 --> <row><v>NaN</v><v>NaN</v><v>NaN</v><v>NaN</v><v>NaN</v></row>
			<!-- 2022-11-09 05:52:30 CST / 1667994750 --> <row><v>NaN</v><v>NaN</v><v>NaN</v><v>NaN</v><v>NaN</v></row>
			<!-- 2022-11-09 05:53:20 CST / 1667994800 --> <row><v>NaN</v><v>NaN</v><v>NaN</v><v>NaN</v><v>NaN</v></row>
			<!-- 2022-11-09 05:54:10 CST / 1667994850 --> <row><v>NaN</v><v>NaN</v><v>NaN</v><v>NaN</v><v>NaN</v></row>
			<!-- 2022-11-09 05:55:00 CST / 1667994900 --> <row><v>NaN</v><v>NaN</v><v>NaN</v><v>NaN</v><v>NaN</v></row>
			<!-- 2022-11-09 05:55:50 CST / 1667994950 --> <row><v>NaN</v><v>NaN</v><v>NaN</v><v>NaN</v><v>NaN</v></row>
			<!-- 2022-11-09 05:56:40 CST / 1667995000 --> <row><v>NaN</v><v>NaN</v><v>NaN</v><v>NaN</v><v>NaN</v></row>
			<!-- 2022-11-09 05:57:30 CST / 1667995050 --> <row><v>NaN</v><v>NaN</v><v>NaN</v><v>NaN</v><v>NaN</v></row>
			<!-- 2022-11-09 05:58:20 CST / 1667995100 --> <row><v>NaN</v><v>NaN</v><v>NaN</v><v>NaN</v><v>NaN</v></row>
			<!-- 2022-11-09 05:59:10 CST / 1667995150 --> <row><v>NaN</v><v>NaN</v><v>NaN</v><v>NaN</v><v>NaN</v></row>
			<!-- 2022-11-09 06:00:00 CST / 1667995200 --> <row><v>NaN</v><v>NaN</v><v>NaN</v><v>NaN</v><v>NaN</v></row>
			<!-- 2022-11-09 06:00:50 CST / 1667995250 --> <row><v>NaN</v><v>NaN</v><v>NaN</v><v>NaN</v><v>NaN</v></row>
			<!-- 2022-11-09 06:01:40 CST / 1667995300 --> <row><v>NaN</v><v>NaN</v><v>NaN</v><v>NaN</v><v>NaN</v></row>
			<!-- 2022-11-09 06:02:30 CST / 1667995350 --> <row><v>NaN</v><v>NaN</v><v>NaN</v><v>NaN</v><v>NaN</v></row>
			<!-- 2022-11-09 06:03:20 CST / 1667995400 --> <row><v>NaN</v><v>NaN</v><v>NaN</v><v>NaN</v><v>NaN</v></row>
			<!-- 2022-11-09 06:04:10 CST / 1667995450 --> <row><v>NaN</v><v>NaN</v><v>NaN</v><v>NaN</v><v>NaN</v></row>
			<!-- 2022-11-09 06:05:00 CST / 1667995500 --> <row><v>NaN</v><v>NaN</v><v>NaN</v><v>NaN</v><v>NaN</v></row>
			<!-- 2022-11-09 06:05:50 CST / 1667995550 --> <row><v>NaN</v><v>NaN</v><v>NaN</v><v>NaN</v><v>NaN</v></row>
			<!-- 2022-11-09 06:06:40 CST / 1667995600 --> <row><v>NaN</v><v>NaN</v><v>NaN</v><v>NaN</v><v>NaN</v></row>
			<!-- 2022-11-09 06:07:30 CST / 1667995650 --> <row><v>NaN</v><v>NaN</v><v>NaN</v><v>NaN</v><v>NaN</v></row>
			<!-- 2022-11-09 06:08:20 CST / 1667995700 --> <row><v>NaN</v><v>NaN</v><v>NaN</v><v>NaN</v><v>NaN</v></row>
			<!-- 2022-11-09 06:09:10 CST / 1667995750 --> <row><v>NaN</v><v>NaN</v><v>NaN</v><v>NaN</v><v>NaN</v></row>
			<!-- 2022-11-09 06:10:00 CST / 1667995800 --> <row><v>NaN</v><v>NaN</v><v>NaN</v><v>NaN</v><v>NaN</v></row>
			<!-- 2022-11-09 06:10:50 CST / 1667995850 --> <row><v>NaN</v><v>NaN</v><v>NaN</v><v>NaN</v><v>NaN</v></row>
			<!-- 2022-11-09 06:11:40 CST / 1667995900 --> <row><v>NaN</v><v>NaN</v><v>NaN</v><v>NaN</v><v>NaN</v></row>
			<!-- 2022-11-09 06:12:30 CST / 1667995950 --> <row><v>NaN</v><v>NaN</v><v>NaN</v><v>NaN</v><v>NaN</v></row>
			<!-- 2022-11-09 06:13:20 CST / 1667996000 --> <row><v>NaN</v><v>NaN</v><v>NaN</v><v>NaN</v><v>NaN</v></row>
			<!-- 2022-11-09 06:14:10 CST / 1667996050 --> <row><v>NaN</v><v>NaN</v><v>NaN</v><v>NaN</v><v>NaN</v></row>
			<!-- 2022-11-09 06:15:00 CST / 1667996100 --> <row><v>NaN</v><v>NaN</v><v>NaN</v><v>NaN</v><v>NaN</v></row>
			<!-- 2022-11-09 06:15:50 CST / 1667996150 --> <row><v>NaN</v><v>NaN</v><v>NaN</v><v>NaN</v><v>NaN</v></row>
			<!-- 2022-11-09 06:16:40 CST / 1667996200 --> <row><v>NaN</v><v>NaN</v><v>NaN</v><v>NaN</v><v>NaN</v></row>
			<!-- 2022-11-09 06:17:30 CST / 1667996250 --> <row><v>NaN</v><v>NaN</v><v>NaN</v><v>NaN</v><v>NaN</v></row>
			<!-- 2022-11-09 06:18:20 CST / 1667996300 --> <row><v>NaN</v><v>NaN</v><v>NaN</v><v>NaN</v><v>NaN</v></row>
			<!-- 2022-11-09 06:19:10 CST / 1667996350 --> <row><v>NaN</v><v>NaN</v><v>NaN</v><v>NaN</v><v>NaN</v></row>
			<!-- 2022-11-09 06:20:00 CST / 1667996400 --> <row><v>NaN</v><v>NaN</v><v>NaN</v><v>NaN</v><v>NaN</v></row>
			<!-- 2022-11-09 06:20:50 CST / 1667996450 --> <row><v>NaN</v><v>NaN</v><v>NaN</v><v>NaN</v><v>NaN</v></row>
			<!-- 2022-11-09 06:21:40 CST / 1667996500 --> <row><v>NaN</v><v>NaN</v><v>NaN</v><v>NaN</v><v>NaN</v></row>
			<!-- 2022-11-09 06:22:30 CST / 1667996550 --> <row><v>NaN</v><v>NaN</v><v>NaN</v><v>NaN</v><v>NaN</v></row>
			<!-- 2022-11-09 06:23:20 CST / 1667996600 --> <row><v>NaN</v><v>NaN</v><v>NaN</v><v>NaN</v><v>NaN</v></row>
			<!-- 2022-11-09 06:24:10 CST / 1667996650 --> <row><v>NaN</v><v>NaN</v><v>NaN</v><v>NaN</v><v>NaN</v></row>
			<!-- 2022-11-09 06:25:00 CST / 1667996700 --> <row><v>NaN</v><v>NaN</v><v>NaN</v><v>NaN</v><v>NaN</v></row>
			<!-- 2022-11-09 06:25:50 CST / 1667996750 --> <row><v>NaN</v><v>NaN</v><v>NaN</v><v>NaN</v><v>NaN</v></row>
			<!-- 2022-11-09 06:26:40 CST / 1667996800 --> <row><v>NaN</v><v>NaN</v><v>NaN</v><v>NaN</v><v>NaN</v></row>
			<!-- 2022-11-09 06:27:30 CST / 1667996850 --> <row><v>NaN</v><v>NaN</v><v>NaN</v><v>NaN</v><v>NaN</v></row>
			<!-- 2022-11-09 06:28:20 CST / 1667996900 --> <row><v>NaN</v><v>NaN</v><v>NaN</v><v>NaN</v><v>NaN</v></row>
			<!-- 2022-11-09 06:29:10 CST / 1667996950 --> <row><v>NaN</v><v>NaN</v><v>NaN</v><v>NaN</v><v>NaN</v></row>
			<!-- 2022-11-09 06:30:00 CST / 1667997000 --> <row><v>NaN</v><v>NaN</v><v>NaN</v><v>NaN</v><v>NaN</v></row>
			<!-- 2022-11-09 06:30:50 CST / 1667997050 --> <row><v>NaN</v><v>NaN</v><v>NaN</v><v>NaN</v><v>NaN</v></row>
			<!-- 2022-11-09 06:31:40 CST / 1667997100 --> <row><v>NaN</v><v>NaN</v><v>NaN</v><v>NaN</v><v>NaN</v></row>
			<!-- 2022-11-09 06:32:30 CST / 1667997150 --> <row><v>NaN</v><v>NaN</v><v>NaN</v><v>NaN</v><v>NaN</v></row>
			<!-- 2022-11-09 06:33:20 CST / 1667997200 --> <row><v>NaN</v><v>NaN</v><v>NaN</v><v>NaN</v><v>NaN</v></row>
			<!-- 2022-11-09 06:34:10 CST / 1667997250 --> <row><v>NaN</v><v>NaN</v><v>NaN</v><v>NaN</v><v>NaN</v></row>
			<!-- 2022-11-09 06:35:00 CST / 1667997300 --> <row><v>NaN</v><v>NaN</v><v>NaN</v><v>NaN</v><v>NaN</v></row>
			<!-- 2022-11-09 06:35:50 CST / 1667997350 --> <row><v>NaN</v><v>NaN</v><v>NaN</v><v>NaN</v><v>NaN</v></row>
			<!-- 2022-11-09 06:36:40 CST / 1667997400 --> <row><v>NaN</v><v>NaN</v><v>NaN</v><v>NaN</v><v>NaN</v></row>
			<!-- 2022-11-09 06:37:30 CST / 1667997450 --> <row><v>NaN</v><v>NaN</v><v>NaN</v><v>NaN</v><v>NaN</v></row>
			<!-- 2022-11-09 06:38:20 CST / 1667997500 --> <row><v>NaN</v><v>NaN</v><v>NaN</v><v>NaN</v><v>NaN</v></row>
			<!-- 2022-11-09 06:39:10 CST / 1667997550 --> <row><v>NaN</v><v>NaN</v><v>NaN</v><v>NaN</v><v>NaN</v></row>
			<!-- 2022-11-09 06:40:00 CST / 1667997600 --> <row><v>NaN</v><v>NaN</v><v>NaN</v><v>NaN</v><v>NaN</v></row>
			<!-- 2022-11-09 06:40:50 CST / 1667997650 --> <row><v>NaN</v><v>NaN</v><v>NaN</v><v>NaN</v><v>NaN</v></row>
			<!-- 2022-11-09 06:41:40 CST / 1667997700 --> <row><v>NaN</v><v>NaN</v><v>NaN</v><v>NaN</v><v>NaN</v></row>
			<!-- 2022-11-09 06:42:30 CST / 1667997750 --> <row><v>NaN</v><v>NaN</v><v>NaN</v><v>NaN</v><v>NaN</v></row>
			<!-- 2022-11-09 06:43:20 CST / 1667997800 --> <row><v>NaN</v><v>NaN</v><v>NaN</v><v>NaN</v><v>NaN</v></row>
			<!-- 2022-11-09 06:44:10 CST / 1667997850 --> <row><v>NaN</v><v>NaN</v><v>NaN</v><v>NaN</v><v>NaN</v></row>
			<!-- 2022-11-09 06:45:00 CST / 1667997900 --> <row><v>NaN</v><v>NaN</v><v>NaN</v><v>NaN</v><v>NaN</v></row>
			<!-- 2022-11-09 06:45:50 CST / 1667997950 --> <row><v>NaN</v><v>NaN</v><v>NaN</v><v>NaN</v><v>NaN</v></row>
			<!-- 2022-11-09 06:46:40 CST / 1667998000 --> <row><v>NaN</v><v>NaN</v><v>NaN</v><v>NaN</v><v>NaN</v></row>
			<!-- 2022-11-09 06:47:30 CST / 1667998050 --> <row><v>NaN</v><v>NaN</v><v>NaN</v><v>NaN</v><v>NaN</v></row>
			<!-- 2022-11-09 06:48:20 CST / 1667998100 --> <row><v>NaN</v><v>NaN</v><v>NaN</v><v>NaN</v><v>NaN</v></row>
			<!-- 2022-11-09 06:49:10 CST / 1667998150 --> <row><v>NaN</v><v>NaN</v><v>NaN</v><v>NaN</v><v>NaN</v></row>
			<!-- 2022-11-09 06:50:00 CST / 1667998200 --> <row><v>NaN</v><v>NaN</v><v>NaN</v><v>NaN</v><v>NaN</v></row>
			<!-- 2022-11-09 06:50:50 CST / 1667998250 --> <row><v>NaN</v><v>NaN</v><v>NaN</v><v>NaN</v><v>NaN</v></row>
			<!-- 2022-11-09 06:51:40 CST / 1667998300 --> <row><v>NaN</v><v>NaN</v><v>NaN</v><v>NaN</v><v>NaN</v></row>
			<!-- 2022-11-09 06:52:30 CST / 1667998350 --> <row><v>NaN</v><v>NaN</v><v>NaN</v><v>NaN</v><v>NaN</v></row>
			<!-- 2022-11-09 06:53:20 CST / 1667998400 --> <row><v>NaN</v><v>NaN</v><v>NaN</v><v>NaN</v><v>NaN</v></row>
			<!-- 2022-11-09 06:54:10 CST / 1667998450 --> <row><v>NaN</v><v>NaN</v><v>NaN</v><v>NaN</v><v>NaN</v></row>
			<!-- 2022-11-09 06:55:00 CST / 1667998500 --> <row><v>NaN</v><v>NaN</v><v>NaN</v><v>NaN</v><v>NaN</v></row>
			<!-- 2022-11-09 06:55:50 CST / 1667998550 --> <row><v>NaN</v><v>NaN</v><v>NaN</v><v>NaN</v><v>NaN</v></row>
			<!-- 2022-11-09 06:56:40 CST / 1667998600 --> <row><v>NaN</v><v>NaN</v><v>NaN</v><v>NaN</v><v>NaN</v></row>
			<!-- 2022-11-09 06:57:30 CST / 1667998650 --> <row><v>NaN</v><v>NaN</v><v>NaN</v><v>NaN</v><v>NaN</v></row>
			<!-- 2022-11-09 06:58:20 CST / 1667998700 --> <row><v>NaN</v><v>NaN</v><v>NaN</v><v>NaN</v><v>NaN</v></row>
			<!-- 2022-11-09 06:59:10 CST / 1667998750 --> <row><v>NaN</v><v>NaN</v><v>NaN</v><v>NaN</v><v>NaN</v></row>
			<!-- 2022-11-09 07:00:00 CST / 1667998800 --> <row><v>NaN</v><v>NaN</v><v>NaN</v><v>NaN</v><v>NaN</v></row>
			<!-- 2022-11-09 07:00:50 CST / 1667998850 --> <row><v>NaN</v><v>NaN</v><v>NaN</v><v>NaN</v><v>NaN</v></row>
			<!-- 2022-11-09 07:01:40 CST / 1667998900 --> <row><v>NaN</v><v>NaN</v><v>NaN</v><v>NaN</v><v>NaN</v></row>
			<!-- 2022-11-09 07:02:30 CST / 1667998950 --> <row><v>NaN</v><v>NaN</v><v>NaN</v><v>NaN</v><v>NaN</v></row>
			<!-- 2022-11-09 07:03:20 CST / 1667999000 --> <row><v>NaN</v><v>NaN</v><v>NaN</v><v>NaN</v><v>NaN</v></row>
			<!-- 2022-11-09 07:04:10 CST / 1667999050 --> <row><v>NaN</v><v>NaN</v><v>NaN</v><v>NaN</v><v>NaN</v></row>
			<!-- 2022-11-09 07:05:00 CST / 1667999100 --> <row><v>NaN</v><v>NaN</v><v>NaN</v><v>NaN</v><v>NaN</v></row>
			<!-- 2022-11-09 07:05:50 CST / 1667999150 --> <row><v>NaN</v><v>NaN</v><v>NaN</v><v>NaN</v><v>NaN</v></row>
			<!-- 2022-11-09 07:06:40 CST / 1667999200 --> <row><v>NaN</v><v>NaN</v><v>NaN</v><v>NaN</v><v>NaN</v></row>
			<!-- 2022-11-09 07:07:30 CST / 1667999250 --> <row><v>1.1210000000e+01</v><v>0.0000000000e+00</v><v>0.0000000000e+00</v><v>2.5400000000e+00</v><v>9.4200000000e+00</v></row>
			<!-- 2022-11-09 07:08:20 CST / 1667999300 --> <row><v>1.1577904709e+01</v><v>0.0000000000e+00</v><v>0.0000000000e+00</v><v>2.6200000000e+00</v><v>1.1080000000e+01</v></row>
		</database>
	</rra>
	<rra>
		<cf>AVERAGE</cf>
		<pdp_per_row>10</pdp_per_row> <!-- 50 seconds -->

		<params>
		<xff>4.0000000000e-01</xff>
		</params>
		<cdp_prep>
			<ds>
			<primary_value>1.1577904709e+01</primary_value>
			<secondary_value>1.0979047090e+01</secondary_value>
			<value>4.4220952910e+01</value>
			<unknown_datapoints>0</unknown_datapoints>
			</ds>
			<ds>
			<primary_value>0.0000000000e+00</primary_value>
			<secondary_value>0.0000000000e+00</secondary_value>
			<value>0.0000000000e+00</value>
			<unknown_datapoints>0</unknown_datapoints>
			</ds>
			<ds>
			<primary_value>0.0000000000e+00</primary_value>
			<secondary_value>0.0000000000e+00</secondary_value>
			<value>0.0000000000e+00</value>
			<unknown_datapoints>0</unknown_datapoints>
			</ds>
			<ds>
			<primary_value>2.6200000000e+00</primary_value>
			<secondary_value>2.6000000000e+00</secondary_value>
			<value>9.6000000000e+00</value>
			<unknown_datapoints>0</unknown_datapoints>
			</ds>
			<ds>
			<primary_value>1.1080000000e+01</primary_value>
			<secondary_value>1.0000000000e+01</secondary_value>
			<value>4.1400000000e+01</value>
			<unknown_datapoints>0</unknown_datapoints>
			</ds>
		</cdp_prep>
		<database>
			<!-- 2022-11-09 05:45:50 CST / 1667994350 --> <row><v>NaN</v><v>NaN</v><v>NaN</v><v>NaN</v><v>NaN</v></row>
			<!-- 2022-11-09 05:46:40 CST / 1667994400 --> <row><v>NaN</v><v>NaN</v><v>NaN</v><v>NaN</v><v>NaN</v></row>
			<!-- 2022-11-09 05:47:30 CST / 1667994450 --> <row><v>NaN</v><v>NaN</v><v>NaN</v><v>NaN</v><v>NaN</v></row>
			<!-- 2022-11-09 05:48:20 CST / 1667994500 --> <row><v>NaN</v><v>NaN</v><v>NaN</v><v>NaN</v><v>NaN</v></row>
			<!-- 2022-11-09 05:49:10 CST / 1667994550 --> <row><v>NaN</v><v>NaN</v><v>NaN</v><v>NaN</v><v>NaN</v></row>
			<!-- 2022-11-09 05:50:00 CST / 1667994600 --> <row><v>NaN</v><v>NaN</v><v>NaN</v><v>NaN</v><v>NaN</v></row>
			<!-- 2022-11-09 05:50:50 CST / 1667994650 --> <row><v>NaN</v><v>NaN</v><v>NaN</v><v>NaN</v><v>NaN</v></row>
			<!-- 2022-11-09 05:51:40 CST / 1667994700 --> <row><v>NaN</v><v>NaN</v><v>NaN</v><v>NaN</v><v>NaN</v></row>
			<!-- 2022-11-09 05:52:30 CST / 1667994750 --> <row><v>NaN</v><v>NaN</v><v>NaN</v><v>NaN</v><v>NaN</v></row>
			<!-- 2022-11-09 05:53:20 CST / 1667994800 --> <row><v>NaN</v><v>NaN</v><v>NaN</v><v>NaN</v><v>NaN</v></row>
			<!-- 2022-11-09 05:54:10 CST / 1667994850 --> <row><v>NaN</v><v>NaN</v><v>NaN</v><v>NaN</v><v>NaN</v></row>
			<!-- 2022-11-09 05:55:00 CST / 1667994900 --> <row><v>NaN</v><v>NaN</v><v>NaN</v><v>NaN</v><v>NaN</v></row>
			<!-- 2022-11-09 05:55:50 CST / 1667994950 --> <row><v>NaN</v><v>NaN</v><v>NaN</v><v>NaN</v><v>NaN</v></row>
			<!-- 2022-11-09 05:56:40 CST / 1667995000 --> <row><v>NaN</v><v>NaN</v><v>NaN</v><v>NaN</v><v>NaN</v></row>
			<!-- 2022-11-09 05:57:30 CST / 1667995050 --> <row><v>NaN</v><v>NaN</v><v>NaN</v><v>NaN</v><v>NaN</v></row>
			<!-- 2022-11-09 05:58:20 CST / 1667995100 --> <row><v>NaN</v><v>NaN</v><v>NaN</v><v>NaN</v><v>NaN</v></row>
			<!-- 2022-11-09 05:59:10 CST / 1667995150 --> <row><v>NaN</v><v>NaN</v><v>NaN</v><v>NaN</v><v>NaN</v></row>
			<!-- 2022-11-09 06:00:00 CST / 1667995200 --> <row><v>NaN</v><v>NaN</v><v>NaN</v><v>NaN</v><v>NaN</v></row>
			<!-- 2022-11-09 06:00:50 CST / 1667995250 --> <row><v>NaN</v><v>NaN</v><v>NaN</v><v>NaN</v><v>NaN</v></row>
			<!-- 2022-11-09 06:01:40 CST / 1667995300 --> <row><v>NaN</v><v>NaN</v><v>NaN</v><v>NaN</v><v>NaN</v></row>
			<!-- 2022-11-09 06:02:30 CST / 1667995350 --> <row><v>NaN</v><v>NaN</v><v>NaN</v><v>NaN</v><v>NaN</v></row>
			<!-- 2022-11-09 06:03:20 CST / 1667995400 --> <row><v>NaN</v><v>NaN</v><v>NaN</v><v>NaN</v><v>NaN</v></row>
			<!-- 2022-11-09 06:04:10 CST / 1667995450 --> <row><v>NaN</v><v>NaN</v><v>NaN</v><v>NaN</v><v>NaN</v></row>
			<!-- 2022-11-09 06:05:00 CST / 1667995500 --> <row><v>NaN</v><v>NaN</v><v>NaN</v><v>NaN</v><v>NaN</v></row>
			<!-- 2022-11-09 06:05:50 CST / 1667995550 --> <row><v>NaN</v><v>NaN</v><v>NaN</v><v>NaN</v><v>NaN</v></row>
			<!-- 2022-11-09 06:06:40 CST / 1667995600 --> <row><v>NaN</v><v>NaN</v><v>NaN</v><v>NaN</v><v>NaN</v></row>
			<!-- 2022-11-09 06:07:30 CST / 1667995650 --> <row><v>NaN</v><v>NaN</v><v>NaN</v><v>NaN</v><v>NaN</v></row>
			<!-- 2022-11-09 06:08:20 CST / 1667995700 --> <row><v>NaN</v><v>NaN</v><v>NaN</v><v>NaN</v><v>NaN</v></row>
			<!-- 2022-11-09 06:09:10 CST / 1667995750 --> <row><v>NaN</v><v>NaN</v><v>NaN</v><v>NaN</v><v>NaN</v></row>
			<!-- 2022-11-09 06:10:00 CST / 1667995800 --> <row><v>NaN</v><v>NaN</v><v>NaN</v><v>NaN</v><v>NaN</v></row>
			<!-- 2022-11-09 06:10:50 CST / 1667995850 --> <row><v>NaN</v><v>NaN</v><v>NaN</v><v>NaN</v><v>NaN</v></row>
			<!-- 2022-11-09 06:11:40 CST / 1667995900 --> <row><v>NaN</v><v>NaN</v><v>NaN</v><v>NaN</v><v>NaN</v></row>
			<!-- 2022-11-09 06:12:30 CST / 1667995950 --> <row><v>NaN</v><v>NaN</v><v>NaN</v><v>NaN</v><v>NaN</v></row>
			<!-- 2022-11-09 06:13:20 CST / 1667996000 --> <row><v>NaN</v><v>NaN</v><v>NaN</v><v>NaN</v><v>NaN</v></row>
			<!-- 2022-11-09 06:14:10 CST / 1667996050 --> <row><v>NaN</v><v>NaN</v><v>NaN</v><v>NaN</v><v>NaN</v></row>
			<!-- 2022-11-09 06:15:00 CST / 1667996100 --> <row><v>NaN</v><v>NaN</v><v>NaN</v><v>NaN</v><v>NaN</v></row>
			<!-- 2022-11-09 06:15:50 CST / 1667996150 --> <row><v>NaN</v><v>NaN</v><v>NaN</v><v>NaN</v><v>NaN</v></row>
			<!-- 2022-11-09 06:16:40 CST / 1667996200 --> <row><v>NaN</v><v>NaN</v><v>NaN</v><v>NaN</v><v>NaN</v></row>
			<!-- 2022-11-09 06:17:30 CST / 1667996250 --> <row><v>NaN</v><v>NaN</v><v>NaN</v><v>NaN</v><v>NaN</v></row>
			<!-- 2022-11-09 06:18:20 CST / 1667996300 --> <row><v>NaN</v><v>NaN</v><v>NaN</v><v>NaN</v><v>NaN</v></row>
			<!-- 2022-11-09 06:19:10 CST / 1667996350 --> <row><v>NaN</v><v>NaN</v><v>NaN</v><v>NaN</v><v>NaN</v></row>
			<!-- 2022-11-09 06:20:00 CST / 1667996400 --> <row><v>NaN</v><v>NaN</v><v>NaN</v><v>NaN</v><v>NaN</v></row>
			<!-- 2022-11-09 06:20:50 CST / 1667996450 --> <row><v>NaN</v><v>NaN</v><v>NaN</v><v>NaN</v><v>NaN</v></row>
			<!-- 2022-11-09 06:21:40 CST / 1667996500 --> <row><v>NaN</v><v>NaN</v><v>NaN</v><v>NaN</v><v>NaN</v></row>
			<!-- 2022-11-09 06:22:30 CST / 1667996550 --> <row><v>NaN</v><v>NaN</v><v>NaN</v><v>NaN</v><v>NaN</v></row>
			<!-- 2022-11-09 06:23:20 CST / 1667996600 --> <row><v>NaN</v><v>NaN</v><v>NaN</v><v>NaN</v><v>NaN</v></row>
			<!-- 2022-11-09 06:24:10 CST / 1667996650 --> <row><v>NaN</v><v>NaN</v><v>NaN</v><v>NaN</v><v>NaN</v></row>
			<!-- 2022-11-09 06:25:00 CST / 1667996700 --> <row><v>NaN</v><v>NaN</v><v>NaN</v><v>NaN</v><v>NaN</v></row>
			<!-- 2022-11-09 06:25:50 CST / 1667996750 --> <row><v>NaN</v><v>NaN</v><v>NaN</v><v>NaN</v><v>NaN</v></row>
			<!-- 2022-11-09 06:26:40 CST / 1667996800 --> <row><v>NaN</v><v>NaN</v><v>NaN</v><v>NaN</v><v>NaN</v></row>
			<!-- 2022-11-09 06:27:30 CST / 1667996850 --> <row><v>NaN</v><v>NaN</v><v>NaN</v><v>NaN</v><v>NaN</v></row>
			<!-- 2022-11-09 06:28:20 CST / 1667996900 --> <row><v>NaN</v><v>NaN</v><v>NaN</v><v>NaN</v><v>NaN</v></row>
			<!-- 2022-11-09 06:29:10 CST / 1667996950 --> <row><v>NaN</v><v>NaN</v><v>NaN</v><v>NaN</v><v>NaN</v></row>
			<!-- 2022-11-09 06:30:00 CST / 1667997000 --> <row><v>NaN</v><v>NaN</v><v>NaN</v><v>NaN</v><v>NaN</v></row>
			<!-- 2022-11-09 06:30:50 CST / 1667997050 --> <row><v>NaN</v><v>NaN</v><v>NaN</v><v>NaN</v><v>NaN</v></row>
			<!-- 2022-11-09 06:31:40 CST / 1667997100 --> <row><v>NaN</v><v>NaN</v><v>NaN</v><v>NaN</v><v>NaN</v></row>
			<!-- 2022-11-09 06:32:30 CST / 1667997150 --> <row><v>NaN</v><v>NaN</v><v>NaN</v><v>NaN</v><v>NaN</v></row>
			<!-- 2022-11-09 06:33:20 CST / 1667997200 --> <row><v>NaN</v><v>NaN</v><v>NaN</v><v>NaN</v><v>NaN</v></row>
			<!-- 2022-11-09 06:34:10 CST / 1667997250 --> <row><v>NaN</v><v>NaN</v><v>NaN</v><v>NaN</v><v>NaN</v></row>
			<!-- 2022-11-09 06:35:00 CST / 1667997300 --> <row><v>NaN</v><v>NaN</v><v>NaN</v><v>NaN</v><v>NaN</v></row>
			<!-- 2022-11-09 06:35:50 CST / 1667997350 --> <row><v>NaN</v><v>NaN</v><v>NaN</v><v>NaN</v><v>NaN</v></row>
			<!-- 2022-11-09 06:36:40 CST / 1667997400 --> <row><v>NaN</v><v>NaN</v><v>NaN</v><v>NaN</v><v>NaN</v></row>
			<!-- 2022-11-09 06:37:30 CST / 1667997450 --> <row><v>NaN</v><v>NaN</v><v>NaN</v><v>NaN</v><v>NaN</v></row>
			<!-- 2022-11-09 06:38:20 CST / 1667997500 --> <row><v>NaN</v><v>NaN</v><v>NaN</v><v>NaN</v><v>NaN</v></row>
			<!-- 2022-11-09 06:39:10 CST / 1667997550 --> <row><v>NaN</v><v>NaN</v><v>NaN</v><v>NaN</v><v>NaN</v></row>
			<!-- 2022-11-09 06:40:00 CST / 1667997600 --> <row><v>NaN</v><v>NaN</v><v>NaN</v><v>NaN</v><v>NaN</v></row>
			<!-- 2022-11-09 06:40:50 CST / 1667997650 --> <row><v>NaN</v><v>NaN</v><v>NaN</v><v>NaN</v><v>NaN</v></row>
			<!-- 2022-11-09 06:41:40 CST / 1667997700 --> <row><v>NaN</v><v>NaN</v><v>NaN</v><v>NaN</v><v>NaN</v></row>
			<!-- 2022-11-09 06:42:30 CST / 1667997750 --> <row><v>NaN</v><v>NaN</v><v>NaN</v><v>NaN</v><v>NaN</v></row>
			<!-- 2022-11-09 06:43:20 CST / 1667997800 --> <row><v>NaN</v><v>NaN</v><v>NaN</v><v>NaN</v><v>NaN</v></row>
			<!-- 2022-11-09 06:44:10 CST / 1667997850 --> <row><v>NaN</v><v>NaN</v><v>NaN</v><v>NaN</v><v>NaN</v></row>
			<!-- 2022-11-09 06:45:00 CST / 1667997900 --> <row><v>NaN</v><v>NaN</v><v>NaN</v><v>NaN</v><v>NaN</v></row>
			<!-- 2022-11-09 06:45:50 CST / 1667997950 --> <row><v>NaN</v><v>NaN</v><v>NaN</v><v>NaN</v><v>NaN</v></row>
			<!-- 2022-11-09 06:46:40 CST / 1667998000 --> <row><v>NaN</v><v>NaN</v><v>NaN</v><v>NaN</v><v>NaN</v></row>
			<!-- 2022-11-09 06:47:30 CST / 1667998050 --> <row><v>NaN</v><v>NaN</v><v>NaN</v><v>NaN</v><v>NaN</v></row>
			<!-- 2022-11-09 06:48:20 CST / 1667998100 --> <row><v>NaN</v><v>NaN</v><v>NaN</v><v>NaN</v><v>NaN</v></row>
			<!-- 2022-11-09 06:49:10 CST / 1667998150 --> <row><v>NaN</v><v>NaN</v><v>NaN</v><v>NaN</v><v>NaN</v></row>
			<!-- 2022-11-09 06:50:00 CST / 1667998200 --> <row><v>NaN</v><v>NaN</v><v>NaN</v><v>NaN</v><v>NaN</v></row>
			<!-- 2022-11-09 06:50:50 CST / 1667998250 --> <row><v>NaN</v><v>NaN</v><v>NaN</v><v>NaN</v><v>NaN</v></row>
			<!-- 2022-11-09 06:51:40 CST / 1667998300 --> <row><v>NaN</v><v>NaN</v><v>NaN</v><v>NaN</v><v>NaN</v></row>
			<!-- 2022-11-09 06:52:30 CST / 1667998350 --> <row><v>NaN</v><v>NaN</v><v>NaN</v><v>NaN</v><v>NaN</v></row>
			<!-- 2022-11-09 06:53:20 CST / 1667998400 --> <row><v>NaN</v><v>NaN</v><v>NaN</v><v>NaN</v><v>NaN</v></row>
			<!-- 2022-11-09 06:54:10 CST / 1667998450 --> <row><v>NaN</v><v>NaN</v><v>NaN</v><v>NaN</v><v>NaN</v></row>
			<!-- 2022-11-09 06:55:00 CST / 1667998500 --> <row><v>NaN</v><v>NaN</v><v>NaN</v><v>NaN</v><v>NaN</v></row>
			<!-- 2022-11-09 06:55:50 CST / 1667998550 --> <row><v>NaN</v><v>NaN</v><v>NaN</v><v>NaN</v><v>NaN</v></row>
			<!-- 2022-11-09 06:56:40 CST / 1667998600 --> <row><v>NaN</v><v>NaN</v><v>NaN</v><v>NaN</v><v>NaN</v></row>
			<!-- 2022-11-09 06:57:30 CST / 1667998650 --> <row><v>NaN</v><v>NaN</v><v>NaN</v><v>NaN</v><v>NaN</v></row>
			<!-- 2022-11-09 06:58:20 CST / 1667998700 --> <row><v>NaN</v><v>NaN</v><v>NaN</v><v>NaN</v><v>NaN</v></row>
			<!-- 2022-11-09 06:59:10 CST / 1667998750 --> <row><v>NaN</v><v>NaN</v><v>NaN</v><v>NaN</v><v>NaN</v></row>
			<!-- 2022-11-09 07:00:00 CST / 1667998800 --> <row><v>NaN</v><v>NaN</v><v>NaN</v><v>NaN</v><v>NaN</v></row>
			<!-- 2022-11-09 07:00:50 CST / 1667998850 --> <row><v>NaN</v><v>NaN</v><v>NaN</v><v>NaN</v><v>NaN</v></row>
			<!-- 2022-11-09 07:01:40 CST / 1667998900 --> <row><v>NaN</v><v>NaN</v><v>NaN</v><v>NaN</v><v>NaN</v></row>
			<!-- 2022-11-09 07:02:30 CST / 1667998950 --> <row><v>NaN</v><v>NaN</v><v>NaN</v><v>NaN</v><v>NaN</v></row>
			<!-- 2022-11-09 07:03:20 CST / 1667999000 --> <row><v>NaN</v><v>NaN</v><v>NaN</v><v>NaN</v><v>NaN</v></row>
			<!-- 2022-11-09 07:04:10 CST / 1667999050 --> <row><v>NaN</v><v>NaN</v><v>NaN</v><v>NaN</v><v>NaN</v></row>
			<!-- 2022-11-09 07:05:00 CST / 1667999100 --> <row><v>NaN</v><v>NaN</v><v>NaN</v><v>NaN</v><v>NaN</v></row>
			<!-- 2022-11-09 07:05:50 CST / 1667999150 --> <row><v>NaN</v><v>NaN</v><v>NaN</v><v>NaN</v><v>NaN</v></row>
			<!-- 2022-11-09 07:06:40 CST / 1667999200 --> <row><v>NaN</v><v>NaN</v><v>NaN</v><v>NaN</v><v>NaN</v></row>
			<!-- 2022-11-09 07:07:30 CST / 1667999250 --> <row><v>1.1210000000e+01</v><v>0.0000000000e+00</v><v>0.0000000000e+00</v><v>2.5400000000e+00</v><v>9.4200000000e+00</v></row>
			<!-- 2022-11-09 07:08:20 CST / 1667999300 --> <row><v>1.1577904709e+01</v><v>0.0000000000e+00</v><v>0.0000000000e+00</v><v>2.6200000000e+00</v><v>1.1080000000e+01</v></row>
		</database>
	</rra>
	<rra>
		<cf>AVERAGE</cf>
		<pdp_per_row>10</pdp_per_row> <!-- 50 seconds -->

		<params>
		<xff>4.0000000000e-01</xff>
		</params>
		<cdp_prep>
			<ds>
			<primary_value>1.1577904709e+01</primary_value>
			<secondary_value>1.0979047090e+01</secondary_value>
			<value>4.4220952910e+01</value>
			<unknown_datapoints>0</unknown_datapoints>
			</ds>
			<ds>
			<primary_value>0.0000000000e+00</primary_value>
			<secondary_value>0.0000000000e+00</secondary_value>
			<value>0.0000000000e+00</value>
			<unknown_datapoints>0</unknown_datapoints>
			</ds>
			<ds>
			<primary_value>0.0000000000e+00</primary_value>
			<secondary_value>0.0000000000e+00</secondary_value>
			<value>0.0000000000e+00</value>
			<unknown_datapoints>0</unknown_datapoints>
			</ds>
			<ds>
			<primary_value>2.6200000000e+00</primary_value>
			<secondary_value>2.6000000000e+00</secondary_value>
			<value>9.6000000000e+00</value>
			<unknown_datapoints>0</unknown_datapoints>
			</ds>
			<ds>
			<primary_value>1.1080000000e+01</primary_value>
			<secondary_value>1.0000000000e+01</secondary_value>
			<value>4.1400000000e+01</value>
			<unknown_datapoints>0</unknown_datapoints>
			</ds>
		</cdp_prep>
		<database>
			<!-- 2022-11-09 05:45:50 CST / 1667994350 --> <row><v>NaN</v><v>NaN</v><v>NaN</v><v>NaN</v><v>NaN</v></row>
			<!-- 2022-11-09 05:46:40 CST / 1667994400 --> <row><v>NaN</v><v>NaN</v><v>NaN</v><v>NaN</v><v>NaN</v></row>
			<!-- 2022-11-09 05:47:30 CST / 1667994450 --> <row><v>NaN</v><v>NaN</v><v>NaN</v><v>NaN</v><v>NaN</v></row>
			<!-- 2022-11-09 05:48:20 CST / 1667994500 --> <row><v>NaN</v><v>NaN</v><v>NaN</v><v>NaN</v><v>NaN</v></row>
			<!-- 2022-11-09 05:49:10 CST / 1667994550 --> <row><v>NaN</v><v>NaN</v><v>NaN</v><v>NaN</v><v>NaN</v></row>
			<!-- 2022-11-09 05:50:00 CST / 1667994600 --> <row><v>NaN</v><v>NaN</v><v>NaN</v><v>NaN</v><v>NaN</v></row>
			<!-- 2022-11-09 05:50:50 CST / 1667994650 --> <row><v>NaN</v><v>NaN</v><v>NaN</v><v>NaN</v><v>NaN</v></row>
			<!-- 2022-11-09 05:51:40 CST / 1667994700 --> <row><v>NaN</v><v>NaN</v><v>NaN</v><v>NaN</v><v>NaN</v></row>
			<!-- 2022-11-09 05:52:30 CST / 1667994750 --> <row><v>NaN</v><v>NaN</v><v>NaN</v><v>NaN</v><v>NaN</v></row>
			<!-- 2022-11-09 05:53:20 CST / 1667994800 --> <row><v>NaN</v><v>NaN</v><v>NaN</v><v>NaN</v><v>NaN</v></row>
			<!-- 2022-11-09 05:54:10 CST / 1667994850 --> <row><v>NaN</v><v>NaN</v><v>NaN</v><v>NaN</v><v>NaN</v></row>
			<!-- 2022-11-09 05:55:00 CST / 1667994900 --> <row><v>NaN</v><v>NaN</v><v>NaN</v><v>NaN</v><v>NaN</v></row>
			<!-- 2022-11-09 05:55:50 CST / 1667994950 --> <row><v>NaN</v><v>NaN</v><v>NaN</v><v>NaN</v><v>NaN</v></row>
			<!-- 2022-11-09 05:56:40 CST / 1667995000 --> <row><v>NaN</v><v>NaN</v><v>NaN</v><v>NaN</v><v>NaN</v></row>
			<!-- 2022-11-09 05:57:30 CST / 1667995050 --> <row><v>NaN</v><v>NaN</v><v>NaN</v><v>NaN</v><v>NaN</v></row>
			<!-- 2022-11-09 05:58:20 CST / 1667995100 --> <row><v>NaN</v><v>NaN</v><v>NaN</v><v>NaN</v><v>NaN</v></row>
			<!-- 2022-11-09 05:59:10 CST / 1667995150 --> <row><v>NaN</v><v>NaN</v><v>NaN</v><v>NaN</v><v>NaN</v></row>
			<!-- 2022-11-09 06:00:00 CST / 1667995200 --> <row><v>NaN</v><v>NaN</v><v>NaN</v><v>NaN</v><v>NaN</v></row>
			<!-- 2022-11-09 06:00:50 CST / 1667995250 --> <row><v>NaN</v><v>NaN</v><v>NaN</v><v>NaN</v><v>NaN</v></row>
			<!-- 2022-11-09 06:01:40 CST / 1667995300 --> <row><v>NaN</v><v>NaN</v><v>NaN</v><v>NaN</v><v>NaN</v></row>
			<!-- 2022-11-09 06:02:30 CST / 1667995350 --> <row><v>NaN</v><v>NaN</v><v>NaN</v><v>NaN</v><v>NaN</v></row>
			<!-- 2022-11-09 06:03:20 CST / 1667995400 --> <row><v>NaN</v><v>NaN</v><v>NaN</v><v>NaN</v><v>NaN</v></row>
			<!-- 2022-11-09 06:04:10 CST / 1667995450 --> <row><v>NaN</v><v>NaN</v><v>NaN</v><v>NaN</v><v>NaN</v></row>
			<!-- 2022-11-09 06:05:00 CST / 1667995500 --> <row><v>NaN</v><v>NaN</v><v>NaN</v><v>NaN</v><v>NaN</v></row>
			<!-- 2022-11-09 06:05:50 CST / 1667995550 --> <row><v>NaN</v><v>NaN</v><v>NaN</v><v>NaN</v><v>NaN</v></row>
			<!-- 2022-11-09 06:06:40 CST / 1667995600 --> <row><v>NaN</v><v>NaN</v><v>NaN</v><v>NaN</v><v>NaN</v></row>
			<!-- 2022-11-09 06:07:30 CST / 1667995650 --> <row><v>NaN</v><v>NaN</v><v>NaN</v><v>NaN</v><v>NaN</v></row>
			<!-- 2022-11-09 06:08:20 CST / 1667995700 --> <row><v>NaN</v><v>NaN</v><v>NaN</v><v>NaN</v><v>NaN</v></row>
			<!-- 2022-11-09 06:09:10 CST / 1667995750 --> <row><v>NaN</v><v>NaN</v><v>NaN</v><v>NaN</v><v>NaN</v></row>
			<!-- 2022-11-09 06:10:00 CST / 1667995800 --> <row><v>NaN</v><v>NaN</v><v>NaN</v><v>NaN</v><v>NaN</v></row>
			<!-- 2022-11-09 06:10:50 CST / 1667995850 --> <row><v>NaN</v><v>NaN</v><v>NaN</v><v>NaN</v><v>NaN</v></row>
			<!-- 2022-11-09 06:11:40 CST / 1667995900 --> <row><v>NaN</v><v>NaN</v><v>NaN</v><v>NaN</v><v>NaN</v></row>
			<!-- 2022-11-09 06:12:30 CST / 1667995950 --> <row><v>NaN</v><v>NaN</v><v>NaN</v><v>NaN</v><v>NaN</v></row>
			<!-- 2022-11-09 06:13:20 CST / 1667996000 --> <row><v>NaN</v><v>NaN</v><v>NaN</v><v>NaN</v><v>NaN</v></row>
			<!-- 2022-11-09 06:14:10 CST / 1667996050 --> <row><v>NaN</v><v>NaN</v><v>NaN</v><v>NaN</v><v>NaN</v></row>
			<!-- 2022-11-09 06:15:00 CST / 1667996100 --> <row><v>NaN</v><v>NaN</v><v>NaN</v><v>NaN</v><v>NaN</v></row>
			<!-- 2022-11-09 06:15:50 CST / 1667996150 --> <row><v>NaN</v><v>NaN</v><v>NaN</v><v>NaN</v><v>NaN</v></row>
			<!-- 2022-11-09 06:16:40 CST / 1667996200 --> <row><v>NaN</v><v>NaN</v><v>NaN</v><v>NaN</v><v>NaN</v></row>
			<!-- 2022-11-09 06:17:30 CST / 1667996250 --> <row><v>NaN</v><v>NaN</v><v>NaN</v><v>NaN</v><v>NaN</v></row>
			<!-- 2022-11-09 06:18:20 CST / 1667996300 --> <row><v>NaN</v><v>NaN</v><v>NaN</v><v>NaN</v><v>NaN</v></row>
			<!-- 2022-11-09 06:19:10 CST / 1667996350 --> <row><v>NaN</v><v>NaN</v><v>NaN</v><v>NaN</v><v>NaN</v></row>
			<!-- 2022-11-09 06:20:00 CST / 1667996400 --> <row><v>NaN</v><v>NaN</v><v>NaN</v><v>NaN</v><v>NaN</v></row>
			<!-- 2022-11-09 06:20:50 CST / 1667996450 --> <row><v>NaN</v><v>NaN</v><v>NaN</v><v>NaN</v><v>NaN</v></row>
			<!-- 2022-11-09 06:21:40 CST / 1667996500 --> <row><v>NaN</v><v>NaN</v><v>NaN</v><v>NaN</v><v>NaN</v></row>
			<!-- 2022-11-09 06:22:30 CST / 1667996550 --> <row><v>NaN</v><v>NaN</v><v>NaN</v><v>NaN</v><v>NaN</v></row>
			<!-- 2022-11-09 06:23:20 CST / 1667996600 --> <row><v>NaN</v><v>NaN</v><v>NaN</v><v>NaN</v><v>NaN</v></row>
			<!-- 2022-11-09 06:24:10 CST / 1667996650 --> <row><v>NaN</v><v>NaN</v><v>NaN</v><v>NaN</v><v>NaN</v></row>
			<!-- 2022-11-09 06:25:00 CST / 1667996700 --> <row><v>NaN</v><v>NaN</v><v>NaN</v><v>NaN</v><v>NaN</v></row>
			<!-- 2022-11-09 06:25:50 CST / 1667996750 --> <row><v>NaN</v><v>NaN</v><v>NaN</v><v>NaN</v><v>NaN</v></row>
			<!-- 2022-11-09 06:26:40 CST / 1667996800 --> <row><v>NaN</v><v>NaN</v><v>NaN</v><v>NaN</v><v>NaN</v></row>
			<!-- 2022-11-09 06:27:30 CST / 1667996850 --> <row><v>NaN</v><v>NaN</v><v>NaN</v><v>NaN</v><v>NaN</v></row>
			<!-- 2022-11-09 06:28:20 CST / 1667996900 --> <row><v>NaN</v><v>NaN</v><v>NaN</v><v>NaN</v><v>NaN</v></row>
			<!-- 2022-11-09 06:29:10 CST / 1667996950 --> <row><v>NaN</v><v>NaN</v><v>NaN</v><v>NaN</v><v>NaN</v></row>
			<!-- 2022-11-09 06:30:00 CST / 1667997000 --> <row><v>NaN</v><v>NaN</v><v>NaN</v><v>NaN</v><v>NaN</v></row>
			<!-- 2022-11-09 06:30:50 CST / 1667997050 --> <row><v>NaN</v><v>NaN</v><v>NaN</v><v>NaN</v><v>NaN</v></row>
			<!-- 2022-11-09 06:31:40 CST / 1667997100 --> <row><v>NaN</v><v>NaN</v><v>NaN</v><v>NaN</v><v>NaN</v></row>
			<!-- 2022-11-09 06:32:30 CST / 1667997150 --> <row><v>NaN</v><v>NaN</v><v>NaN</v><v>NaN</v><v>NaN</v></row>
			<!-- 2022-11-09 06:33:20 CST / 1667997200 --> <row><v>NaN</v><v>NaN</v><v>NaN</v><v>NaN</v><v>NaN</v></row>
			<!-- 2022-11-09 06:34:10 CST / 1667997250 --> <row><v>NaN</v><v>NaN</v><v>NaN</v><v>NaN</v><v>NaN</v></row>
			<!-- 2022-11-09 06:35:00 CST / 1667997300 --> <row><v>NaN</v><v>NaN</v><v>NaN</v><v>NaN</v><v>NaN</v></row>
			<!-- 2022-11-09 06:35:50 CST / 1667997350 --> <row><v>NaN</v><v>NaN</v><v>NaN</v><v>NaN</v><v>NaN</v></row>
			<!-- 2022-11-09 06:36:40 CST / 1667997400 --> <row><v>NaN</v><v>NaN</v><v>NaN</v><v>NaN</v><v>NaN</v></row>
			<!-- 2022-11-09 06:37:30 CST / 1667997450 --> <row><v>NaN</v><v>NaN</v><v>NaN</v><v>NaN</v><v>NaN</v></row>
			<!-- 2022-11-09 06:38:20 CST / 1667997500 --> <row><v>NaN</v><v>NaN</v><v>NaN</v><v>NaN</v><v>NaN</v></row>
			<!-- 2022-11-09 06:39:10 CST / 1667997550 --> <row><v>NaN</v><v>NaN</v><v>NaN</v><v>NaN</v><v>NaN</v></row>
			<!-- 2022-11-09 06:40:00 CST / 1667997600 --> <row><v>NaN</v><v>NaN</v><v>NaN</v><v>NaN</v><v>NaN</v></row>
			<!-- 2022-11-09 06:40:50 CST / 1667997650 --> <row><v>NaN</v><v>NaN</v><v>NaN</v><v>NaN</v><v>NaN</v></row>
			<!-- 2022-11-09 06:41:40 CST / 1667997700 --> <row><v>NaN</v><v>NaN</v><v>NaN</v><v>NaN</v><v>NaN</v></row>
			<!-- 2022-11-09 06:42:30 CST / 1667997750 --> <row><v>NaN</v><v>NaN</v><v>NaN</v><v>NaN</v><v>NaN</v></row>
			<!-- 2022-11-09 06:43:20 CST / 1667997800 --> <row><v>NaN</v><v>NaN</v><v>NaN</v><v>NaN</v><v>NaN</v></row>
			<!-- 2022-11-09 06:44:10 CST / 1667997850 --> <row><v>NaN</v><v>NaN</v><v>NaN</v><v>NaN</v><v>NaN</v></row>
			<!-- 2022-11-09 06:45:00 CST / 1667997900 --> <row><v>NaN</v><v>NaN</v><v>NaN</v><v>NaN</v><v>NaN</v></row>
			<!-- 2022-11-09 06:45:50 CST / 1667997950 --> <row><v>NaN</v><v>NaN</v><v>NaN</v><v>NaN</v><v>NaN</v></row>
			<!-- 2022-11-09 06:46:40 CST / 1667998000 --> <row><v>NaN</v><v>NaN</v><v>NaN</v><v>NaN</v><v>NaN</v></row>
			<!-- 2022-11-09 06:47:30 CST / 1667998050 --> <row><v>NaN</v><v>NaN</v><v>NaN</v><v>NaN</v><v>NaN</v></row>
			<!-- 2022-11-09 06:48:20 CST / 1667998100 --> <row><v>NaN</v><v>NaN</v><v>NaN</v><v>NaN</v><v>NaN</v></row>
			<!-- 2022-11-09 06:49:10 CST / 1667998150 --> <row><v>NaN</v><v>NaN</v><v>NaN</v><v>NaN</v><v>NaN</v></row>
			<!-- 2022-11-09 06:50:00 CST / 1667998200 --> <row><v>NaN</v><v>NaN</v><v>NaN</v><v>NaN</v><v>NaN</v></row>
			<!-- 2022-11-09 06:50:50 CST / 1667998250 --> <row><v>NaN</v><v>NaN</v><v>NaN</v><v>NaN</v><v>NaN</v></row>
			<!-- 2022-11-09 06:51:40 CST / 1667998300 --> <row><v>NaN</v><v>NaN</v><v>NaN</v><v>NaN</v><v>NaN</v></row>
			<!-- 2022-11-09 06:52:30 CST / 1667998350 --> <row><v>NaN</v><v>NaN</v><v>NaN</v><v>NaN</v><v>NaN</v></row>
			<!-- 2022-11-09 06:53:20 CST / 1667998400 --> <row><v>NaN</v><v>NaN</v><v>NaN</v><v>NaN</v><v>NaN</v></row>
			<!-- 2022-11-09 06:54:10 CST / 1667998450 --> <row><v>NaN</v><v>NaN</v><v>NaN</v><v>NaN</v><v>NaN</v></row>
			<!-- 2022-11-09 06:55:00 CST / 1667998500 --> <row><v>NaN</v><v>NaN</v><v>NaN</v><v>NaN</v><v>NaN</v></row>
			<!-- 2022-11-09 06:55:50 CST / 1667998550 --> <row><v>NaN</v><v>NaN</v><v>NaN</v><v>NaN</v><v>NaN</v></row>
			<!-- 2022-11-09 06:56:40 CST / 1667998600 --> <row><v>NaN</v><v>NaN</v><v>NaN</v><v>NaN</v><v>NaN</v></row>
			<!-- 2022-11-09 06:57:30 CST / 1667998650 --> <row><v>NaN</v><v>NaN</v><v>NaN</v><v>NaN</v><v>NaN</v></row>
			<!-- 2022-11-09 06:58:20 CST / 1667998700 --> <row><v>NaN</v><v>NaN</v><v>NaN</v><v>NaN</v><v>NaN</v></row>
			<!-- 2022-11-09 06:59:10 CST / 1667998750 --> <row><v>NaN</v><v>NaN</v><v>NaN</v><v>NaN</v><v>NaN</v></row>
			<!-- 2022-11-09 07:00:00 CST / 1667998800 --> <row><v>NaN</v><v>NaN</v><v>NaN</v><v>NaN</v><v>NaN</v></row>
			<!-- 2022-11-09 07:00:50 CST / 1667998850 --> <row><v>NaN</v><v>NaN</v><v>NaN</v><v>NaN</v><v>NaN</v></row>
			<!-- 2022-11-09 07:01:40 CST / 1667998900 --> <row><v>NaN</v><v>NaN</v><v>NaN</v><v>NaN</v><v>NaN</v></row>
			<!-- 2022-11-09 07:02:30 CST / 1667998950 --> <row><v>NaN</v><v>NaN</v><v>NaN</v><v>NaN</v><v>NaN</v></row>
			<!-- 2022-11-09 07:03:20 CST / 1667999000 --> <row><v>NaN</v><v>NaN</v><v>NaN</v><v>NaN</v><v>NaN</v></row>
			<!-- 2022-11-09 07:04:10 CST / 1667999050 --> <row><v>NaN</v><v>NaN</v><v>NaN</v><v>NaN</v><v>NaN</v></row>
			<!-- 2022-11-09 07:05:00 CST / 1667999100 --> <row><v>NaN</v><v>NaN</v><v>NaN</v><v>NaN</v><v>NaN</v></row>
			<!-- 2022-11-09 07:05:50 CST / 1667999150 --> <row><v>NaN</v><v>NaN</v><v>NaN</v><v>NaN</v><v>NaN</v></row>
			<!-- 2022-11-09 07:06:40 CST / 1667999200 --> <row><v>NaN</v><v>NaN</v><v>NaN</v><v>NaN</v><v>NaN</v></row>
			<!-- 2022-11-09 07:07:30 CST / 1667999250 --> <row><v>1.1210000000e+01</v><v>0.0000000000e+00</v><v>0.0000000000e+00</v><v>2.5400000000e+00</v><v>9.4200000000e+00</v></row>
			<!-- 2022-11-09 07:08:20 CST / 1667999300 --> <row><v>1.1577904709e+01</v><v>0.0000000000e+00</v><v>0.0000000000e+00</v><v>2.6200000000e+00</v><v>1.1080000000e+01</v></row>
		</database>
	</rra>
</rrd>
